Workbook

Sheet RESUMEN CHART

Sheet resumen
D1: FECHA | E1: 45263 | Q1: DIFERENCIAS
A3: TIPO DE CAMBIO CCL | B3: 1450 | C3: % | D3: LOCAL | E3: SB | F3: SB LETNA
A4: BONOS GUBERNAMENTALES | B4: =SUM(D4:F4) -> 7845975.6 | C4: =+B4/$B$12 -> 0.68158614 | D4: =+D65 -> 91380.523 | E4: 3183784.4 | F4: 4570810.7 | G4: 4,570,810.65 | H4: $3,183,784.40
A5: ACCIONES/OPCIONES/fondos acciones | B5: =SUM(D5:F5) -> 0 | C5: =+B5/$B$12 -> 0 | D5: 0 | I5: 0
A6: LIQUIDEZ | B6: =SUM(D6:F6) -> 297162.52 | C6: =+B6/$B$12 -> 0.025814744 | D6: =+D43 -> 297162.52 | I6: 874410.1
A7: hsbc MIAMI | B7: =SUM(D7:F7) -> 474789.31 | C7: =+B7/$B$12 -> 0.041245325 | D7: 474789.31 | I7: 0
A8: FONDOS /ETF/comodities | B8: =SUM(D8:F8) -> 0 | C8: =+B8/$B$12 -> 0 | D8: 0 | I8: 0
A9: HIPOTECAS | B9: =SUM(D9:F9) -> 660 | C9: =+B9/$B$12 -> 5.7334725e-05 | D9: =+CARTERA!D652 -> 660 | H9: 10904.91 | I9: 95800
A10: INMUEBLES/INCLUYE TRACKER | B10: =SUM(D10:F10) -> 2892761.1 | C10: =+B10/$B$12 -> 0.25129646 | D10: =143288*1.1+2735144.28896578 -> 2892761.1 | E10: 0 | F10: 0 | I10: 2735144.3
B11: =SUM(D11:E11) -> 0 | C11: =+B11/$B$12 -> 0
B12: =SUM(B4:B11) -> 11511348 | C12: =SUM(C4:C11) -> 1 | D12: =SUM(D4:D11) -> 3756753.4 | E12: =SUM(E4:E10) -> 3183784.4 | F12: =SUM(F4:F10) -> 4570810.7
A13: AÑO 2001 | B13: =+#REF!*1000 -> #REF!
A14: DIFERENCIA | B14: =+B12-B13 -> #REF!
G15: 246421.1
G16: 523211.46
G17: =+G15+G16 -> 769632.56
V23: =+H152+H141 -> 120752.59 | W23: 0 | X23: =+J152+J141 -> 95458.831 | Y23: =+K152+K141 -> 23029.09 | Z23: =+L152+L141 -> 2264.67
V34: =+V23+H163 -> 131815.37 | W34: =+W23+I163 -> 1 | X34: =+X23+J163 -> 99614.907 | Y34: =+Y23+K163 -> 30958.79 | Z34: =+Z23+L163 -> 1241.67
A35: RESUMEN EFECTIVO EN MONEDA EXTRANJERA | D35: =+CARTERA!C19 -> 235474.66
F36: NO CONSIDERADO EN EL CUADRO
A39: subtotal | D39: =SUM(D35:D38) -> 235474.66
A40: PLAZO FIJOS EN PESOS+FONDOS | D40: =+CARTERA!C20 -> 89447394
A41: COHEN CAUCION/MARIA | D41: 0
A42: INVERSIONES SMITH BARNEY | D42: 0
A43: TOTAL | D43: =+D39+(D40+D41)/B3+D42 -> 297162.52
V45: =+V34+H174 -> 22425.866
A46: total dolares | W46: =+W34+I174 -> 2 | X46: =+X34+J174 -> 43938.096 | Y46: =+Y34+K174 -> -12112.8 | Z46: =+Z34+L174 -> -9399.43
A48: POSICION ACTUAL AL 31/01/16 | J48: Nombre de la Especie | K48: Cantidad | L48: Precio | M48: Importe
A49: Especie | B49: Cantidad Total | C49: Cotizacion | D49: Valor de Mercado | G49: BONOS EN DOLARES | I49: COTIZACION AFUERA | J49: 00007 ALUAR ALUMINIO ARG. S.AI.I.C. | K49: 20,174.0000000 | L49: 9470 | M49: 191,047.78
A50: BONOS EN DOLARES | C50: COTIZACION AFUERA | D50: DOLARES | E50: PESOS | J50: 00251 COMERCIAL DEL PLATA | K50: 4,600.0000000 | L50: 3300 | M50: 15,180.00
J51: 00457 PAMPA ENERGIA S.A. | K51: 15,000.0000000 | L51: 12750 | M51: 191,250.00
J52: 00633 IRSA "B" | K52: 2,000.0000000 | L52: 14950 | M52: 29,900.00
G53: DICEEXT | H53: 200000 | I53: 1.41 | J53: 00804 PETROBRAS ENERGIA S.A. | K53: 18,352.0000000 | L53: 8600 | M53: 157,827.20
C54: 1.6 | F54: =+E54/$B$3 -> 0 | G54: PARA | H54: 270000 | I54: 0.55 | J54: 00807 TELECOM S.A. | K54: 3,900.0000000 | L54: 45000 | M54: 175,500.00 | V54: =+V45+H183 -> 26237.109
C55: 0.65 | F55: =+E55/$B$3 -> 0 | G55: PAA0 | H55: 20000 | I55: 0.55 | J55: 00839 SIDERAR -A- 1 VOTO | K55: 4,485.0000000 | L55: 7900 | M55: 35,431.50 | Y55: =+Y46+K183 -> -12112.8 | Z55: =+Z46+L183 -> -9399.43
C56: 0.65 | F56: =+E56/$B$3 -> 0 | G56: DICY | H56: 150000 | I56: 1.41 | J56: 30031 PETROLERA PAMPA S.A. ORD. 1 VOTO $ ESC. | K56: 1,362.0000000 | L56: 32450 | M56: 44,196.90
C57: 1.6 | F57: =+E57/$B$3 -> 0 | G57: GJ17 | H57: 100000 | I57: 1 | M57: _________________________
A58: BONOS EN DOLARES | C58: 1.1 | D58: 0 | F58: =+E58/$B$3 -> 0 | L58: ACCIONES | M58: 840,333.38
D59: =SUM(D51:D58) -> 0 | E59: =SUM(E51:E58) -> 0 | J59: 02405 NF18 - BONOS GARANT. DECRETO 1579/02 $ | K59: 243,990.0000000 | L59: 127500 | M59: 311,087.25
G60: TOTAL RESUMEN COHEN $ | J60: 05445 BONOS REP.ARG. A LA PAR USD 2010/2038 | K60: 20,000.0000000 | L60: 880000 | M60: 176,000.00
A61: TOTAL RESUMEN COHEN $ | G61: SALDO EN ACCIONES Y TITULOS $ | H61: LECAP | J61: 40785 VALORES NEG VINC PBI EURO V.2035 | K61: 369,495.0000000 | L61: 161000 | M61: 594,886.95
A62: SALDO EN ACCIONES Y TITULOS $ | E62: 132501758 | F62: 12648940 | G62: 197457 | H62: 162,247.80 | J62: 40786 BONOS C/DESCUENTO EUROS STEP | K62: 200,000.0000000 | L62: 1875000 | M62: 3,750,000.00
A63: COHEN U$S | D63: 0 | E63: 0 | G63: Pases y Cauciones a Liquidar 83,769.62 | J63: 44672 GJ17- BONOS GLOBALES 2017 U$S 2010/2017 | K63: 100,000.0000000 | L63: 1545000 | M63: 1,545,000.00
A64: EN U$S OFICIAL | E64: =+E62/B3+E63 -> 91380.523 | G64: -319.144 | J64: 44674 B.REP.ARG DIS CJ.PRE05-PAR-QUASI USD2033. | K64: 250,000.0000000 | L64: 2140000 | M64: 5,350,000.00
A65: TOTAL u$S | D65: =SUM(D59:D64)+E64 -> 91380.523 | J65: 45695 PARP-BONO PAR $ STEP UP 2038 | K65: 40,707.0000000 | L65: 251500 | M65: 102,378.11
J66: 45699 PARA- BONO PAR U$S STEP UP 12/2038 | K66: 270,000.0000000 | L66: 905000 | M66: 2,443,500.00
M67: _________________________
L68: TITULOS PUBLICOS | M68: 14,272,852.31 | V68: =+V54+H196 -> 129338.3
J69: 06000 EUROS | K69: 0.2500000 | L69: 13960 | M69: 3.49 | W69: =+#REF!+I196 -> #REF! | X69: =+#REF!+J196 -> #REF!
J70: 07000 DOLARES USA (CABLE) | K70: 0.0700000 | L70: 13960 | M70: 0.98 | Y70: =+Y55+K196 -> 32753.66 | Z70: =+Z55+L196 -> -165.09
M71: _________________________
L72: MONEDA | M72: 4.47
J73: PESOS | M73: 134.74
M74: _________________________
L75: CUENTA CORRIENTE | M75: 134.74
M76: _________________________
L77: TOTAL | M77: 15,113,324.89
D79: SB | E79: SCH | V79: =+V68+H207 -> 154972.94
B80: 36951 | C80: 200000 | W80: =+W69+I207 -> #REF! | X80: =+X69+J207 -> #REF!
B81: 37398 | C81: 95000 | Y81: =+Y70+K207 -> 12514.37 | Z81: =+Z70+L207 -> 424.91
B82: 37412 | C82: 74000 | D82: =SUM(C80:C87) -> 697000 | E82: =+D82-E90-E91 -> 318000
B83: 37425 | C83: 90000
B84: 37449 | C84: 18000
B85: 37497 | C85: 100000
B86: 37607 | C86: 90000
B87: 37701 | C87: 30000 | D87: =+E82 -> 318000
A88: SCHCOL | B88: 38139 | C88: 5000
A89: SCHCOL | B89: 38988 | C89: -5000
A90: SM | B90: 38169 | C90: 52800 | D90: =+C90 -> 52800 | E90: 168000 | V90: =+V79+H218 -> 229411.53
A91: SM | B91: 38261 | C91: 49900 | D91: =+C91 -> 49900 | E91: 211000 | W91: =+W80+I218 -> #REF! | X91: =+X80+J218 -> #REF!
A92: SCH | B92: 38572 | C92: 65000 | E92: =+C92 -> 65000 | Y92: =+Y81+K218 -> 57774.14 | Z92: =+Z81+L218 -> 12600.48
A93: SCH | B93: 38597 | C93: 50000 | E93: =+C93 -> 50000
A94: SM | B94: 38898 | C94: 50000 | D94: =+C94 -> 50000
A95: SM | B95: 38936 | C95: 50000 | D95: =+C95 -> 50000
A96: SCH | B96: 39035 | C96: 50000 | E96: =+C96 -> 50000
A97: SCH | B97: 39092 | C97: 50000 | E97: =+C97 -> 50000
A98: SM | B98: 39259 | C98: 50000 | D98: =+C98 -> 50000
A99: SCH | B99: 39304 | C99: 50000 | E99: =+C99 -> 50000 | F99: GASTOS
A100: SB | B100: 40102 | C100: 50000 | D100: 50000 | F100: -50
A101: SB | B101: 40106 | C101: 50000 | D101: 50000 | F101: -50 | V101: =+V90+H229 -> 344769.19
A102: SB | B102: 40534 | C102: 50000 | D102: 50000 | F102: 250 | W102: =+W91+I229 -> #REF! | X102: =+X91+J229 -> #REF!
A103: SB | B103: 40535 | C103: 50000 | D103: 50000 | F103: 250 | Y103: =+Y92+K229 -> 87610.62 | Z103: =+Z92+L229 -> 19249.49
A104: SCH | B104: 41394 | C104: =2800+4752*1.3 -> 8977.6 | E104: =+C104 -> 8977.6
A105: SB | B105: 41582 | D105: 50000 | F105: 125
A106: SCH | B106: 41635 | C106: 50000 | E106: =+C106 -> 50000 | F106: -125
D108: =SUM(D80:D104) -> 1467700 | E108: =SUM(E80:E104) -> 970977.6 | F108: =SUM(F87:F107) -> 400
A110: SB OK | B110: 42578 | C110: 53800 EUROS DESDE BBVA | D110: 53800
B114: TOTAL | C114: =SUM(C80:C110) -> 1473677.6
D115: =+F5 -> 0
B116: SB | C116: =+D115 -> 0 | D116: =+D115-D108 -> -1467700 | V116: =+V101+H240 -> 368281.46
B117: HSBC | C117: 0 | W117: =+W102+I240 -> #REF! | X117: =+X102+J240 -> #REF!
B118: SCH | C118: =+E115 -> 0 | Y118: =+Y103+K240 -> 84651.51 | Z118: =+Z103+L240 -> 16382.91
B119: TOTAL ACTUAL | C119: =SUM(C116:C118) -> 0 | D119: 41912
B121: DIFERENCIA | C121: =+C119-C114 -> -1473677.6 | D121: =+C121/C114 -> -1
B123: DOL-EUR | C123: =150000/0.97 -> 154639.18 | D123: EN AÑOS
B124: INTERESES EURO | C124: 4000
C125: =+C124+C123 -> 158639.18
C126: =+C125*1.312 -> 208134.6
B127: DOL | C127: 150000 | V127: =+V116+H251 -> 545243.47
C128: =+C126-C127 -> 58134.598 | W128: =+W117+I251 -> #REF! | X128: =+X117+J251 -> #REF!
...

Sheet UVA
A1: UVA
A2: FECHA | B2: Valor | C2: Columna1 | D2: 45170 | E2: 12,7 | G2: 2024 | H2: - | I2: Variación | K2: 2023 | L2: - | M2: Variación
A3: 45139 | B3: 292.58 | I3: porcentual | M3: porcentual | O3: UF010 | S3: 0.06
A4: 45140 | B4: 293.13 | I4: mes | M4: mes | O4: CONCEPTO | P4: FECHA | Q4: importes | R4: en UVAs | S4: intereses | U4: HABER
A5: 45141 | B5: 293.68 | I5: anterior | M5: anterior
A6: 45142 | B6: 294.23 | G6: Enero | I6: 0.206 | K6: Enero | M6: 0.06 | O6: Alquiler agosto 2023 | P6: 45148 | Q6: 155000 | R6: =+Q6/VLOOKUP(P6,TablaUVA[#All],2) -> 520.88584 | S6: =+R6*$S$3*($P$31-P6)/360 -> 22.918977 | U6: 0
A7: 45143 | B7: 294.78 | G7: Febrero | I7: 0.132 | K7: Febrero | M7: 0.066 | O7: BBVA DEBITO | P7: 45164 | Q7: =-U7 -> -160000 | R7: =+Q7/VLOOKUP(P7,TablaUVA[#All],2) -> -521.2915 | S7: =+R7*$S$3*($P$31-P7)/360 -> -21.546715 | U7: 160000
A8: 45144 | B8: 294.78 | G8: Marzo | I8: 0.11 | K8: Marzo | M8: 0.077 | O8: BBVA DEBITO | P8: 45166 | Q8: =-U8 -> -90000 | R8: =+Q8/VLOOKUP(P8,TablaUVA[#All],2) -> -293.22647 | S8: =+R8*$S$3*($P$31-P8)/360 -> -12.022285 | U8: 90000
A9: 45145 | B9: 294.78 | G9: Abril | I9: 0.088 | K9: Abril | M9: 0.084 | O9: BBVA DEBITO | P9: 45171 | Q9: =-U9 -> -63000 | R9: =+Q9/VLOOKUP(P9,TablaUVA[#All],2) -> -202.44216 | S9: =+R9*$S$3*($P$31-P9)/360 -> -8.1314267 | U9: 63000
A10: 45146 | B10: 296.45 | G10: Mayo | I10: 0.042 | K10: Mayo | M10: 0.078 | O10: Alquiler septiembre 2023 | P10: 45179 | Q10: 155000 | R10: =+Q10/VLOOKUP(P10,TablaUVA[#All],2) -> 491.25254 | S10: =+R10*$S$3*($P$31-P10)/360 -> 19.076973 | U10: 0
A11: 45147 | B11: 297.01 | G11: Junio | I11: 0.046 | K11: Junio | M11: 0.06 | O11: Alquiler octubre 2023 | P11: 45209 | Q11: 155000 | R11: =+Q11/VLOOKUP(P11,TablaUVA[#All],2) -> 441.26858 | S11: =+R11*$S$3*($P$31-P11)/360 -> 14.929587 | U11: 0
A12: 45148 | B12: 297.57 | G12: Julio | I12: 0.04 | K12: Julio | M12: 0.063 | O12: BBVA DEBITO | P12: 45231 | Q12: =-U12 -> -165000 | R12: =+Q12/VLOOKUP(P12,TablaUVA[#All],2) -> -431.41766 | S12: =+R12*$S$3*($P$31-P12)/360 -> -13.014433 | U12: 165000
A13: 45149 | B13: 298.13 | G13: Agosto | I13: 0.042 | K13: Agosto | M13: 0.124 | O13: Alquiler noviembre 2023 | P13: 45240 | Q13: 213000 | R13: =+Q13/VLOOKUP(P13,TablaUVA[#All],2) -> 537.93312 | S13: =+R13*$S$3*($P$31-P13)/360 -> 15.42075 | U13: 0
A14: 45150 | B14: 298.69 | G14: Septiembre | I14: 0.035 | K14: Septiembre | M14: 0.127 | O14: BBVA DEBITO | P14: 45264 | Q14: =-U14 -> -103000 | R14: =+Q14/VLOOKUP(P14,TablaUVA[#All],2) -> -243.59096 | S14: =+R14*$S$3*($P$31-P14)/360 -> -6.0085769 | U14: 103000
A15: 45151 | B15: 298.69 | G15: Octubre | I15: 0.027 | K15: Octubre | M15: 0.083 | O15: Alquiler diciembre 2023 | P15: 45270 | Q15: 213000 | R15: =+Q15/VLOOKUP(P15,TablaUVA[#All],2) -> 495.7639 | S15: =+R15*$S$3*($P$31-P15)/360 -> 11.733079 | U15: 0
A16: 45152 | B16: 298.69 | G16: Noviembre | I16: 0.027 | K16: Noviembre | M16: 0.128 | O16: BBVA DEBITO | P16: 45290 | Q16: =-U16 -> -120000 | R16: =+Q16/VLOOKUP(P16,TablaUVA[#All],2) -> -258.95555 | S16: =+R16*$S$3*($P$31-P16)/360 -> -5.2654294 | U16: 120000
A17: 45153 | B17: 300.38 | G17: Diciembre | I17: 0.03 | K17: Diciembre | M17: 0.255 | O17: BBVA DEBITO | P17: 45296 | Q17: =-U17 -> -150000 | R17: =+Q17/VLOOKUP(P17,TablaUVA[#All],2) -> -316.23553 | S17: =+R17*$S$3*($P$31-P17)/360 -> -6.113887 | U17: 150000
A18: 45154 | B18: 300.94 | O18: Alquiler enero 2024 | P18: 45301 | Q18: 213000 | R18: =+Q18/VLOOKUP(P18,TablaUVA[#All],2) -> 440.41022 | S18: =+R18*$S$3*($P$31-P18)/360 -> 8.1475891 | U18: 0
A19: 45155 | B19: 301.54 | K19: 2025 | L19: - | M19: Variación | O19: TRANSFERENCIA adelanto EXPENSAS | P19: 45321 | Q19: 110523.54 | R19: =+Q19/VLOOKUP(P19,TablaUVA[#All],2) -> 201.49409 | S19: =+R19*$S$3*($P$31-P19)/360 -> 3.0559937
A20: 45156 | B20: 302.13 | M20: porcentual | O20: Alquiler FEBRERO 2024 | P20: 45332 | Q20: 364000 | R20: =+Q20/VLOOKUP(P20,TablaUVA[#All],2) -> 612.21744 | S20: =+R20*$S$3*($P$31-P20)/360 -> 8.1628992 | U20: 0
A21: 45157 | B21: 302.73 | M21: mes | O21: BBVA DEBITO | P21: 45345 | Q21: -75000 | R21: =+Q21/VLOOKUP(P21,TablaUVA[#All],2) -> -115.38284 | S21: =+R21*$S$3*($P$31-P21)/360 -> -1.2884417 | U21: 200000
A22: 45158 | B22: 302.73 | M22: anterior | O22: BBVA DEBITO | P22: 45352 | Q22: =-U21 -> -200000 | R22: =+Q22/VLOOKUP(P22,TablaUVA[#All],2) -> -294.08305 | S22: =+R22*$S$3*($P$31-P22)/360 -> -2.9408305 | U22: 0
A23: 45159 | B23: 302.73 | K23: Enero | M23: 0.022 | O23: Alquiler MARZO 2024 | P23: 45361 | Q23: 364000 | R23: =+Q23/VLOOKUP(P23,TablaUVA[#All],2) -> 508.2805 | S23: =+R23*$S$3*($P$31-P23)/360 -> 4.3203843 | U23: 100000
A24: 45160 | B24: 302.73 | K24: Febrero | M24: 0.024 | O24: BBVA DEBITO | P24: 45363 | Q24: =-U23 -> -100000 | R24: =+Q24/VLOOKUP(P24,TablaUVA[#All],2) -> -136.95816 | S24: =+R24*$S$3*($P$31-P24)/360 -> -1.1184916 | U24: 60000
A25: 45161 | B25: 305.12 | K25: Marzo | M25: 0.037 | O25: BBVA DEBITO | P25: 45367 | Q25: =-U24 -> -60000 | R25: =+Q25/VLOOKUP(P25,TablaUVA[#All],2) -> -80.079011 | S25: =+R25*$S$3*($P$31-P25)/360 -> -0.60059258
K26: Abril | M26: 0.028 | O26: TRANSFERENCIA adelanto EXPENSAS | P26: 45372 | Q26: 125000 | R26: =+Q26/VLOOKUP(P26,TablaUVA[#All],2) -> 163.52695 | S26: =+R26*$S$3*($P$31-P26)/360 -> 1.0901797
A27: 45162 | B27: 305.72 | K27: Mayo | M27: 0.015 | O27: Alquiler MARZO 2024 | P27: 45392 | Q27: 364000 | R27: =+Q27/VLOOKUP(P27,TablaUVA[#All],2) -> 439.58698 | S27: =+R27*$S$3*($P$31-P27)/360 -> 1.4652899
A28: 45163 | B28: 306.33 | K28: Junio | M28: 0.016 | O28: BBVA DEBITO | P28: 45394 | Q28: -860000 | R28: =+Q28/VLOOKUP(P28,TablaUVA[#All],2) -> -1030.3103 | S28: =+R28*$S$3*($P$31-P28)/360 -> -3.0909309
A29: 45164 | B29: 306.93 | K29: Julio | M29: =+M28 -> 0.016 | O29: total nominales historicos | Q29: =SUM(Q6:Q28) -> 285523.54 | R29: =SUM(R6:R28) -> 928.64698 | S29: =SUM(S6:S28) -> 29.179661
A30: 45165 | B30: 306.93 | K30: Agosto | M30: =+M29 -> 0.016
A31: 45166 | B31: 306.93 | K31: Septiembre | M31: =+M30 -> 0.016 | O31: DEUDA EN PESOS AL | P31: 45412 | R31: =+R29*VLOOKUP(P31,TablaUVA[#All],2) -> 826950.85 | S31: =+S29*VLOOKUP(P31,TablaUVA[#All],2) -> 25984.196
A32: 45167 | B32: 308.75 | K32: Octubre | M32: =+M31 -> 0.016
A33: 45168 | B33: 309.36 | K33: Noviembre | M33: =+M32 -> 0.016
A34: 45169 | B34: 309.97 | C34: =(+TablaUVA[[#This Row],[Valor]]-B3)/B3 -> 0.059436735 | K34: Diciembre | M34: =+M33 -> 0.016
A35: 45170 | B35: 310.58 | S35: 45488
A36: 45171 | B36: 311.2 | O36: FECHA | P36: DEPOSITADO | Q36: ACOBRAR | R36: VTO. | S36: DIAS | T36: TASA | U36: BANCO | V36: intereses | W36: UVA INICIO | X36: UVA VTO. | Y36: UVA DEPOS
A37: 45172 | B37: 311.2 | O37: 45306 | P37: 193200 | Q37: =+P37*(1+T37) -> 421789.74 | R37: =+O37+S37 -> 45488 | S37: =+$S$35-O37 -> 182 | T37: =+(+X37*(1+0.01/365*S37))/W37-1 -> 1.1831767 | V37: =+Q37-P37 -> 228589.74 | W37: =VLOOKUP(O37,TablaUVA[#All],2) -> 489.31 | X37: =VLOOKUP($S$35,TablaUVA[#All],2) -> 1062.95 | Y37: 4272.7665
A38: 45173 | B38: 311.2 | O38: 45307 | P38: 95900 | Q38: =+P38*(1+T38*S38/365) -> 150962.49 | R38: =+O38+S38 -> 45488 | S38: =+$S$35-O38 -> 181 | T38: =+(+X38*(1+0.01/365*S38))/W38-1 -> 1.157848 | V38: =+Q38-P38 -> 55062.492 | W38: =VLOOKUP(O38,TablaUVA[#All],2) -> 495.04 | X38: =VLOOKUP($S$35,TablaUVA[#All],2) -> 1062.95 | Y38: 1335.7042
A39: 45174 | B39: 313.04 | O39: 45310 | P39: 115000 | Q39: =+P39*(1+T39*S39/365) -> 177292.04 | R39: =+O39+S39 -> 45488 | S39: =+$S$35-O39 -> 178 | T39: =+(+X39*(1+0.01/365*S39))/W39-1 -> 1.1107276 | V39: =+Q39-P39 -> 62292.038 | W39: =VLOOKUP(O39,TablaUVA[#All],2) -> 506.05 | X39: =VLOOKUP($S$35,TablaUVA[#All],2) -> 1062.95 | Y39: 485.8986
A40: 45175 | B40: 313.66 | O40: 45315 | P40: 98600 | Q40: =+P40*(1+T40*S40/365) -> 146947.61 | R40: =+O40+S40 -> 45488 | S40: =+$S$35-O40 -> 173 | T40: =+(+X40*(1+0.01/365*S40))/W40-1 -> 1.0345343 | V40: =+Q40-P40 -> 48347.614 | W40: =VLOOKUP(O40,TablaUVA[#All],2) -> 524.93 | X40: =VLOOKUP($S$35,TablaUVA[#All],2) -> 1062.95 | Y40: 341.28357
A41: 45176 | B41: 314.28 | O41: 45316 | P41: 190700 | Q41: =+P41*(1+T41*S41/365) -> 282327.94 | R41: =+O41+S41 -> 45488 | S41: =+$S$35-O41 -> 172 | T41: =+(+X41*(1+0.01/365*S41))/W41-1 -> 1.0196278 | V41: =+Q41-P41 -> 91627.942 | W41: =VLOOKUP(O41,TablaUVA[#All],2) -> 528.79 | X41: =VLOOKUP($S$35,TablaUVA[#All],2) -> 1062.95 | Y41: 355.52683
A42: 45177 | B42: 314.9 | O42: 45355 | P42: 113600 | Q42: =+P42*(1+T42*S42/365) -> 136722.23 | R42: =+O42+S42 -> 45488 | S42: =+$S$35-O42 -> 133 | T42: =+(+X42*(1+0.01/365*S42))/W42-1 -> 0.55858932 | V42: =+Q42-P42 -> 23122.231 | W42: =VLOOKUP(O42,TablaUVA[#All],2) -> 684.48 | X42: =VLOOKUP($S$35,TablaUVA[#All],2) -> 1062.95 | Y42: 227.25027
A43: 45178 | B43: 315.52 | O43: 45362 | P43: 400000 | Q43: =+P43*(1+T43*S43/365) -> 467577.51 | R43: =+O43+S43 -> 45488 | S43: =+$S$35-O43 -> 126 | T43: =+(+X43*(1+0.01/365*S43))/W43-1 -> 0.48940062 | V43: =+Q43-P43 -> 67577.511 | W43: =VLOOKUP(O43,TablaUVA[#All],2) -> 716.14 | X43: =VLOOKUP($S$35,TablaUVA[#All],2) -> 1062.95 | Y43: 266.70223
A44: 45179 | B44: 315.52 | O44: 45366 | P44: 400000 | Q44: =+P44*(1+T44*S44/365) -> 457841.28 | R44: =+O44+S44 -> 45488 | S44: =+$S$35-O44 -> 122 | T44: =+(+X44*(1+0.01/365*S44))/W44-1 -> 0.43262435 | V44: =+Q44-P44 -> 57841.283 | W44: =VLOOKUP(O44,TablaUVA[#All],2) -> 744.44 | X44: =VLOOKUP($S$35,TablaUVA[#All],2) -> 1062.95 | Y44: 671.65611
A45: 45180 | B45: 315.52 | O45: 45366 | P45: 300000 | Q45: =+P45*(1+T45*S45/365) -> 343380.96 | R45: =+O45+S45 -> 45488 | S45: =+$S$35-O45 -> 122 | T45: =+(+X45*(1+0.01/365*S45))/W45-1 -> 0.43262435 | V45: =+Q45-P45 -> 43380.963 | W45: =VLOOKUP(O45,TablaUVA[#All],2) -> 744.44 | X45: =VLOOKUP($S$35,TablaUVA[#All],2) -> 1062.95 | Y45: 1101.0864
O46: 45369 | P46: 400000 | Q46: =+P46*(1+T46*S46/365) -> 455201.87 | R46: 45469 | S46: =+$S$35-O46 -> 119 | T46: =+(+X46*(1+0.01/365*S46))/W46-1 -> 0.42329166 | V46: 313269.64 | W46: =VLOOKUP(O46,TablaUVA[#All],2) -> 749.26 | X46: =VLOOKUP($S$35,TablaUVA[#All],2) -> 1062.95 | Y46: 1101.0864
O47: 45376 | P47: 629998 | Q47: =+P47*(1+T47*S47/365) -> 704176.63 | R47: =+O47+S47 -> 45488 | S47: =+$S$35-O47 -> 112 | T47: =+(+X47*(1+0.01/365*S47))/W47-1 -> 0.38372006 | V47: =+Q47-P47 -> 74178.634 | W47: =VLOOKUP(O47,TablaUVA[#All],2) -> 770.54 | X47: =VLOOKUP($S$35,TablaUVA[#All],2) -> 1062.95 | Y47: 1101.0864
O48: 45376 | P48: 65000 | Q48: =+P48*(1+T48*S48/365) -> 72653.375 | R48: =+O48+S48 -> 45488 | S48: =+$S$35-O48 -> 112 | T48: =+(+X48*(1+0.01/365*S48))/W48-1 -> 0.38372006 | V48: =+Q48-P48 -> 7653.3754 | W48: =VLOOKUP(O48,TablaUVA[#All],2) -> 770.54 | X48: =VLOOKUP($S$35,TablaUVA[#All],2) -> 1062.95 | Y48: 1101.0864
A49: 45181 | B49: 317.39 | O49: 45377 | P49: 500000 | Q49: =+P49*(1+T49*S49/365) -> 555831.65 | R49: =+O49+S49 -> 45488 | S49: =+$S$35-O49 -> 111 | T49: =+(+X49*(1+0.01/365*S49))/W49-1 -> 0.36718113 | V49: =+Q49-P49 -> 55831.651 | W49: =VLOOKUP(O49,TablaUVA[#All],2) -> 779.84 | X49: =VLOOKUP($S$35,TablaUVA[#All],2) -> 1062.95 | Y49: 9.6296439
A50: 45182 | B50: 318.02 | O50: 45392 | P50: 65900 | Q50: =+P50*(1+T50*S50/365) -> 70875.406 | R50: =+O50+S50 -> 45488 | S50: =+$S$35-O50 -> 96 | T50: =+(+X50*(1+0.01/365*S50))/W50-1 -> 0.28705477 | V50: =+Q50-P50 -> 4975.4063 | W50: =VLOOKUP(O50,TablaUVA[#All],2) -> 828.05 | X50: =VLOOKUP($S$35,TablaUVA[#All],2) -> 1062.95 | Y50: 10.629644
A51: 45183 | B51: 318.64 | O51: 45414 | P51: 500000 | Q51: =+P51*(1+T51*S51/365) -> 519455.51 | R51: =+O51+S51 -> 45488 | S51: =+$S$35-O51 -> 74 | T51: =+(+X51*(1+0.01/365*S51))/W51-1 -> 0.19192594 | V51: =+Q51-P51 -> 19455.506 | W51: =VLOOKUP(O51,TablaUVA[#All],2) -> 893.6 | X51: =VLOOKUP($S$35,TablaUVA[#All],2) -> 1062.95 | Y51: 11.629644
A52: 45184 | B52: 319.27 | O52: 45483 | P52: 990000 | Q52: =+P52*(1+T52*S52/365) -> 990076.4 | R52: =+O52+S52 -> 45488 | S52: =+$S$35-O52 -> 5 | T52: =+(+X52*(1+0.01/365*S52))/W52-1 -> 0.0056337 | V52: =+Q52-P52 -> 76.402233 | W52: =VLOOKUP(O52,TablaUVA[#All],2) -> 1057.14 | X52: =VLOOKUP($S$35,TablaUVA[#All],2) -> 1062.95 | Y52: 12.629644
A53: 45185 | B53: 319.9
A54: 45186 | B54: 319.9
A55: 45187 | B55: 319.9 | P55: =SUM(P37:P54) -> 5057898 | Q55: =SUM(Q37:Q54) -> 5953112.7
A56: 45188 | B56: 323.66
A57: 45189 | B57: 324.93
A58: 45190 | B58: 326.19
A59: 45191 | B59: 327.47
A60: 45192 | B60: 328.75
A61: 45193 | B61: 328.75
A62: 45194 | B62: 328.75
A63: 45195 | B63: 332.61
A64: 45196 | B64: 333.91
A65: 45197 | B65: 335.21
A66: 45198 | B66: 336.52
A67: 45199 | B67: 337.84 | C67: =(+TablaUVA[[#This Row],[Valor]]-B34)/B34 -> 0.089911927
A68: 45200 | B68: 337.84
A69: 45201 | B69: 337.84
A70: 45202 | B70: 341.81
A71: 45203 | B71: 343.14
A72: 45204 | B72: 344.48
A73: 45205 | B73: 345.83
A74: 45206 | B74: 347.18
A75: 45207 | B75: 347.18
A76: 45208 | B76: 347.18
A77: 45209 | B77: 351.26
A78: 45210 | B78: 352.63
A79: 45211 | B79: 354.01
... A97: 45229 | B97: 376.6
A98: 45230 | B98: 380.98 | C98: =(+TablaUVA[[#This Row],[Valor]]-B68)/B68 -> 0.12769358
A99: 45231 | B99: 382.46
A100: 45232 | B100: 383.93
A101: 45233 | B101: 385.42
A102: 45234 | B102: 386.91
A103: 45235 | B103: 386.91
A104: 45236 | B104: 386.91
A105: 45237 | B105: 386.91
A106: 45238 | B106: 392.92
A107: 45239 | B107: 394.44
A108: 45240 | B108: 395.96
A109: 45241 | B109: 397.49
A110: 45242 | B110: 397.49
... A127: 45259 | B127: 419.48
A128: 45260 | B128: 420.6 | C128: =(+TablaUVA[[#This Row],[Valor]]-B99)/B99 -> 0.099722847
A129: 45261 | B129: 421.72
A130: 45262 | B130: 422.84
A131: 45263 | B131: 422.84
A132: 45264 | B132: 422.84
A133: 45265 | B133: 426.22
...

Sheet CARTERA
A1: AGREGAR UNOS
C3: 58291 | J3: 90
A4: CERA | C4: 0
A5: miami | C5: 0 | J5: 90
A6: CAJA DE AHORRO | C6: =720+62565.63 -> 63285.63
A7: caja | C7: 0
A8: FONDO REATRIACION/PFIJO | C8: =+C47 -> 0
A9: SUBTOTAL | C9: =SUM(C3:C8) -> 121576.63 | F9: =+C9+resumen!H1951 -> 295205.78
A10: caja de ahorro ITAU | C10: 22463.01
A11: unicreidt | C11: 16686
C12: 53340
A13: kate Personal | C13: =2000+5000+1000+500 -> 8500
A14: depto via albertini | B14: 143288.48 | C14: 0
A15: CAJA | C15: 705.66 | G15: =SUM(G16:G18) -> 4065.01
A16: LIBRAS | C16: =1*50+15*20+1*10+3*5 -> 375 | F16: =SUM(#REF!) -> #REF! | G16: 3046.88
A17: TOTAL DOLARES | C17: =+C9 -> 121576.63 | G17: 960.63
A18: TOTAL EUROS | B18: 1.12 | C18: =SUM(C10:C15) -> 101694.67 | G18: 57.5
C19: =+(C17+C18*B18) -> 235474.66 | G19: 37912
A20: TOTAL LIQUIDO PESOS | C20: =+C624 -> 89447394 | G20: 180
C21: =SUM(C23:C30) -> 674000 | F21: =SUM(C23:C30) -> 674000 | G21: =+F24+#REF! -> #REF! | H21: =141000+41000+24000 -> 206000
A22: FECHA | B22: DEPOSITADO | C22: ACOBRAR | D22: VTO. | E22: DIAS | F22: TASA | G22: BANCO | J22: 90
A23: 45883 | B23: 31076.77 | C23: 30000 | D23: =+E23+A23 -> 45976 | E23: 93 | F23: =+C23*4.375%/2 -> 656.25 | G23: Invetna | H23: 15-05-34 -Coupon Rate 4.375%; Matures 05/15/2034; CUSIP 91282CKQ3 | J23: 90
A24: 45547 | B24: 216000 | C24: 216000 | D24: 45976 | E24: 184 | F24: =+C24*4.375%/2 -> 4725 | G24: Invetna | H24: 15-05-34 -Coupon Rate 4.375%; Matures 05/15/2034; CUSIP 91282CKQ3 | I24: =+F24*2/B24 -> 0.04375
B25: 53000 | C25: 53000 | D25: 45976 | E25: 184 | F25: =+C25*4.375%/2 -> 1159.375 | G25: HSBC MIAMI | H25: 31-05-28 -UNITED STATES TREAS NTS 4,375% 05/31/28 B/E DTD 05/31/23 1ST CPN DTE 11/30/23 CPN PMT SEMI ANNUAL ON MAY 31 AND NOV 30 | J25: 90
A26: 45701 | B26: 100000 | C26: 100000 | D26: 45976 | E26: 166 | F26: =+C26*4.375%/2 -> 2187.5 | G26: sb Personal | H26: 15-05-34 -Coupon Rate 4.375%; Matures 05/15/2034; CUSIP 91282CKQ3 | J26: 90
A27: 45713 | B27: 51002.93 | C27: 52000 | D27: 45989 | E27: 180 | F27: 1997.07 | G27: HSBC MIAMI | H27: LETRAS DEL TESORO
B28: 125000 | C28: 125000 | D28: 45991 | E28: 184 | F28: =+C28*4.875%/2 -> 3046.875 | G28: HSBC MIAMI | H28: 31-5-26 -UNITED STATES TREAS NTS 4.875% 05/31/26 B/E DTD 05/31/24 1ST CPN DTE 11/30/24 CPN PMT SEMI ANNUAL ON MAY 31 AND NOV 30
A29: 45519 | B29: 53000 | C29: 53000 | D29: 45991 | E29: 183 | F29: =+C29*3.625%/2 -> 960.625 | G29: HSBC MIAMI | H29: 15-05-34 -UNITED STATES TREAS NTS 3.625% 05/31/28 B/E DTD 05/31/23 1ST CPN DTE 11/30/23 CPN PMT SEMI ANNUAL ON MAY 31 AND NOV 30
A30: 45810 | B30: 45000 | C30: 45000 | D30: 45991 | E30: 183 | F30: =+C30*4.125%/2 -> 928.125 | G30: sb Personal | H30: 30-11-09 -Coupon Rate 4.125%; Matures 11/30/2029; CUSIP 91282CMA6 | J30: 90
A31: 45679 | B31: 57000 | C31: 57000 | D31: 46008 | E31: 329 | F31: =+C31*4.25%/2 -> 1211.25 | G31: HSBC MIAMI | H31: 30-6-29 -UNITED STATES TREAS NTS 4.250% 06/30/29 B/E DTD 06/30/24 1ST CPN DTE 12/31/24 CPN PMT SEMI ANNUAL ON JUN 30 AND DEC 31 | I31: CADA 6 MESES | J31: 90
A32: 45838 | B32: 165000 | C32: 165000 | D32: =+A32+E32 -> 46021 | E32: 183 | F32: =+C32*4.25%/2 -> 3506.25 | G32: sb Personal | H32: 30-06-29 -Coupon Rate 4.250%; Matures 06/30/2029; CUSIP 91282CKX8 | J32: 37
A33: 45858 | B33: 140000 | C33: =+B33 -> 140000 | D33: =+A33+E33 -> 46042 | E33: 184 | F33: =+C33*7.125%/2 -> 4987.5 | G33: Invetna | H33: 20-01-37 -Coupon Rate 7.125%; Matures 01/20/2037; CUSIP 105756BK5, COUPON PAYABLE SEMI-ANNUALLY ON JANUARY AND JULY 20th | I33: =+F33*2/B33 -> 0.07125 | J33: 37
A34: 45858 | B34: =21000+125000 -> 146000 | C34: =+B34 -> 146000 | D34: =+A34+E34 -> 46042 | E34: 184 | F34: =+C34*7.125%/2 -> 5201.25 | G34: sb Personal | H34: 20-01-37 -Coupon Rate 7.125%; Matures 01/20/2037; CUSIP 105756BK5, COUPON PAYABLE SEMI-ANNUALLY ON JANUARY AND JULY 20th | J34: 90
A35: 45890 | B35: 25614.11 | C35: 26000 | D35: =+A35+E35 -> 46053 | E35: 163 | F35: =+C35-B35 -> 385.89 | G35: HSBC MIAMI | H35: LETRAS DEL TESORO | J35: 90
A36: 45870 | B36: =36000+33000 -> 69000 | C36: =+B36 -> 69000 | D36: =+E36+A36 -> 46054 | E36: 184 | F36: =+C36*3.65%/2 -> 1259.25 | G36: sb Personal | H36: 01-0835 -COUPON 3,65% SEMESTRE 1/2 Y 1/8 VTO 1/8/2035. - Symbol / CUSIP / ISIN: - T6025AAC8-IT0005631590 | J36: 90
A37: 45884 | B37: 50000 | C37: 50000 | D37: =+A37+E37 -> 46068 | E37: 184 | F37: 1000 | G37: HSBC MIAMI | H37: 15-02-34 -UNITED STATES TREAS NTS 4.000% 02/15/34 B/E DTD 02/15/24 1ST CPN DTE 08/15/24 CPN PMT SEMI ANNUAL ON FEB 15 AND AUG 15 | I37: 45000
A38: 45884 | B38: =206000+35000 -> 241000 | C38: =+B38 -> 241000 | D38: =+A38+E38 -> 46068 | E38: 184 | F38: =+C38*4%/2 -> 4820 | G38: sb Personal | H38: 15-02-34 -Coupon Rate 4.000%; Matures 02/15/2034; CUSIP 91282CJZ5
A39: 45638 | B39: 30305.83 | C39: 37000 | D39: 47529 | E39: 0 | G39: HSBC MIAMI | H39: 15-02-30 -ZERO CPN UNITED STATES TREAS SEC STRIPPED INT PMT STRIP INT OF 30-YR BOND 5.375 DUE 0.000% 02/15/30 B/E DTD 02/15/01 | I39: CADA 6 MESES
A40: 45808 | B40: 23760.35 | C40: 36000 | D40: 49171 | E40: 0 | G40: HSBC MIAMI | H40: 15-08-34 -ZERO CPN UNITED STATES TREAS SEC STRIPPED INT PMT STRIP INT OF 30-YR BOND 4.50% DUE 02-15-2036 INT RATE 0.000% MATURITY 08/15/2034 DATED 02/15/2006 BOOK ENTRY ONLY ZERO CPN BD SUBJ TO FED TAX
B42: =SUBTOTAL(109,B23:B40) -> 1621760 | C42: =SUBTOTAL(109,C23:C40) -> 1641000 | E42: =MEDIAN(E29:E37) -> 184 | F42: =SUM(F23:F40) -> 38032.21
C43: =+C42-B42 -> 19240.01 | D43: =+C43/B42*2 -> 0.023727321 | F43: =SUBTOTAL(9,F23:F38) -> 38032.21 | H43: =SUM(H29:H31) -> 0 | I43: Columna2
A44: FECHA | B44: DEPOSITADO | C44: =SUM(C36:C40) -> 433000 | D44: VTO. | E44: DIAS | F44: TASA | G44: BANCO | H44: Columna1
C45: 27657.985
B47: =SUM(B46) -> 0 | C47: =SUM(C46) -> 0
C48: =+C47-B47 -> 0
A50: PLAZO FIJO AFUERA | B50: =+B42 -> 1621760 | C50: =+C42 -> 1641000
B51: =+B47+B50 -> 1621760 | C51: =+C47+C50 -> 1641000
A53: PLAZO FIJO LOCALES | B53: =SUBTOTAL(109,' PF ANTERIORES U$S'!B538:B538) -> 58256 | C53: =+C47 -> 0
A58: CAJA DE AHORRO DOLARES | C58: 104993.16 | D58: =SUM(#REF!) -> #REF! | H58: =2.88*12 -> 34.56
A59: BBVA DOLARES | C59: 2240.59
A60: TOTAL DOLARES | C60: =+C53+C58 -> 104993.16
A61: CAJA DE AHORRO EUROS | H61: =SUM(#REF!) -> #REF!
E62: =A62+D62 -> 0 | H62: =SUM(#REF!) -> #REF!
A63: FECHA | B63: DEPOSITADO | C63: ACOBRAR | D63: VTO. | E63: DIAS | F63: TASA | G63: BANCO | H63: Columna8 | I63: Columna9 | J63: Columna10 | K63: Columna11 | L63: Columna12 | M63: Columna13
A64: 45915 | B64: 185000 | C64: =B64+(B64*F64/365*E64)*1 -> 195182.6 | D64: =+A64+E64 -> 45964 | E64: 49 | F64: 0.41 | G64: BBVA BANCO RAMONA | H64: =(C64-B64)/E64*30 -> 6234.2466 | I64: =VLOOKUP(Tabla1[[#This Row],[FECHA]],TablaUVA[#All],2) -> 1581.0787 | J64: =VLOOKUP(Tabla1[[#This Row],[VTO.]],TablaUVA[#All],2) -> 1622.9309 | K64: =+Tabla1[[#This Row],[DEPOSITADO]]/I64 -> 117.00872 | L64: =IF(Tabla1[[#This Row],[DIAS]]>89,+K64*J64*(1+1%/365*Tabla1[[#This Row],[DIAS]]),Tabla1[[#This Row],[ACOBRAR]]) -> 195182.6 | M64: =+L64-Tabla1[[#This Row],[ACOBRAR]] -> 0
A65: 45915 | B65: 621000 | C65: =B65+(B65*F65/365*E65)*1 -> 656014.19 | D65: =+A65+E65 -> 45964 | E65: 49 | F65: 0.42 | G65: ITAU BANCO | H65: =(C65-B65)/E65*30 -> 21437.26 | I65: =VLOOKUP(Tabla1[[#This Row],[FECHA]],TablaUVA[#All],2) -> 1581.0787 | J65: =VLOOKUP(Tabla1[[#This Row],[VTO.]],TablaUVA[#All],2) -> 1622.9309 | K65: =+Tabla1[[#This Row],[DEPOSITADO]]/I65 -> 392.76981 | L65: =IF(Tabla1[[#This Row],[DIAS]]>89,+K65*J65*(1+1%/365*Tabla1[[#This Row],[DIAS]]),Tabla1[[#This Row],[ACOBRAR]]) -> 656014.19 | M65: =+L65-Tabla1[[#This Row],[ACOBRAR]] -> 0
A66: 45915 | B66: 1280000 | C66: =B66+(B66*F66/365*E66)*1 -> 1353889.3 | D66: =+A66+E66 -> 45964 | E66: 49 | F66: 0.43 | G66: BNA RAMONA | H66: =(C66-B66)/E66*30 -> 45238.356 | I66: =VLOOKUP(Tabla1[[#This Row],[FECHA]],TablaUVA[#All],2) -> 1581.0787 | J66: =VLOOKUP(Tabla1[[#This Row],[VTO.]],TablaUVA[#All],2) -> 1622.9309 | K66: =+Tabla1[[#This Row],[DEPOSITADO]]/I66 -> 809.57385 | L66: =IF(Tabla1[[#This Row],[DIAS]]>89,+K66*J66*(1+1%/365*Tabla1[[#This Row],[DIAS]]),Tabla1[[#This Row],[ACOBRAR]]) -> 1353889.3 | M66: =+L66-Tabla1[[#This Row],[ACOBRAR]] -> 0
A67: 45915 | B67: 920000 | C67: =B67+(B67*F67/365*E67)*1 -> 974343.01 | D67: =+A67+E67 -> 45964 | E67: 49 | F67: 0.44 | G67: HSBC BANCO | H67: =(C67-B67)/E67*30 -> 33271.233 | I67: =VLOOKUP(Tabla1[[#This Row],[FECHA]],TablaUVA[#All],2) -> 1581.0787 | J67: =VLOOKUP(Tabla1[[#This Row],[VTO.]],TablaUVA[#All],2) -> 1622.9309 | K67: =+Tabla1[[#This Row],[DEPOSITADO]]/I67 -> 581.8812 | L67: =IF(Tabla1[[#This Row],[DIAS]]>89,+K67*J67*(1+1%/365*Tabla1[[#This Row],[DIAS]]),Tabla1[[#This Row],[ACOBRAR]]) -> 974343.01 | M67: =+L67-Tabla1[[#This Row],[ACOBRAR]] -> 0
A68: 45912 | B68: 400000 | C68: =B68+(B68*F68/365*E68)*1 -> 423364.38 | D68: =+A68+E68 -> 45964 | E68: 52 | F68: 0.41 | G68: BBVA BANCO RAMONA | H68: =(C68-B68)/E68*30 -> 13479.452 | I68: =VLOOKUP(Tabla1[[#This Row],[FECHA]],TablaUVA[#All],2) -> 1578.5517 | J68: =VLOOKUP(Tabla1[[#This Row],[VTO.]],TablaUVA[#All],2) -> 1622.9309 | K68: =+Tabla1[[#This Row],[DEPOSITADO]]/I68 -> 253.39683 | L68: =IF(Tabla1[[#This Row],[DIAS]]>89,+K68*J68*(1+1%/365*Tabla1[[#This Row],[DIAS]]),Tabla1[[#This Row],[ACOBRAR]]) -> 423364.38 | M68: =+L68-Tabla1[[#This Row],[ACOBRAR]] -> 0
A69: 45917 | B69: 800000 | C69: =B69+(B69*F69/365*E69)*1 -> 842082.19 | D69: =+A69+E69 -> 45965 | E69: 48 | F69: 0.4 | G69: HSBC BANCO | H69: =(C69-B69)/E69*30 -> 26301.37 | I69: =VLOOKUP(Tabla1[[#This Row],[FECHA]],TablaUVA[#All],2) -> 1582.7657 | J69: =VLOOKUP(Tabla1[[#This Row],[VTO.]],TablaUVA[#All],2) -> 1623.7965 | K69: =+Tabla1[[#This Row],[DEPOSITADO]]/I69 -> 505.44437 | L69: =IF(Tabla1[[#This Row],[DIAS]]>89,+K69*J69*(1+1%/365*Tabla1[[#This Row],[DIAS]]),Tabla1[[#This Row],[ACOBRAR]]) -> 842082.19 | M69: =+L69-Tabla1[[#This Row],[ACOBRAR]] -> 0
A70: 45916 | B70: 381000 | C70: =B70+(B70*F70/365*E70)*1 -> 402993.62 | D70: =+A70+E70 -> 45965 | E70: 49 | F70: 0.43 | G70: BNA BANCO | H70: =(C70-B70)/E70*30 -> 13465.479 | I70: =VLOOKUP(Tabla1[[#This Row],[FECHA]],TablaUVA[#All],2) -> 1581.922 | J70: =VLOOKUP(Tabla1[[#This Row],[VTO.]],TablaUVA[#All],2) -> 1623.7965 | K70: =+Tabla1[[#This Row],[DEPOSITADO]]/I70 -> 240.84626 | L70: =IF(Tabla1[[#This Row],[DIAS]]>89,+K70*J70*(1+1%/365*Tabla1[[#This Row],[DIAS]]),Tabla1[[#This Row],[ACOBRAR]]) -> 402993.62 | M70: =+L70-Tabla1[[#This Row],[ACOBRAR]] -> 0
A71: 45916 | B71: 496000 | C71: =B71+(B71*F71/365*E71)*1 -> 523966.25 | D71: =+A71+E71 -> 45965 | E71: 49 | F71: 0.42 | G71: ITAU BANCO | H71: =(C71-B71)/E71*30 -> 17122.192 | I71: =VLOOKUP(Tabla1[[#This Row],[FECHA]],TablaUVA[#All],2) -> 1581.922 | J71: =VLOOKUP(Tabla1[[#This Row],[VTO.]],TablaUVA[#All],2) -> 1623.7965 | K71: =+Tabla1[[#This Row],[DEPOSITADO]]/I71 -> 313.54264 | L71: =IF(Tabla1[[#This Row],[DIAS]]>89,+K71*J71*(1+1%/365*Tabla1[[#This Row],[DIAS]]),Tabla1[[#This Row],[ACOBRAR]]) -> 523966.25 | M71: =+L71-Tabla1[[#This Row],[ACOBRAR]] -> 0
A72: 45916 | B72: 755000 | C72: =B72+(B72*F72/365*E72)*1 -> 795542.47 | D72: =+A72+E72 -> 45965 | E72: 49 | F72: 0.4 | G72: HSBC BANCO | H72: =(C72-B72)/E72*30 -> 24821.918 | I72: =VLOOKUP(Tabla1[[#This Row],[FECHA]],TablaUVA[#All],2) -> 1581.922 | J72: =VLOOKUP(Tabla1[[#This Row],[VTO.]],TablaUVA[#All],2) -> 1623.7965 | K72: =+Tabla1[[#This Row],[DEPOSITADO]]/I72 -> 477.26753 | L72: =IF(Tabla1[[#This Row],[DIAS]]>89,+K72*J72*(1+1%/365*Tabla1[[#This Row],[DIAS]]),Tabla1[[#This Row],[ACOBRAR]]) -> 795542.47 | M72: =+L72-Tabla1[[#This Row],[ACOBRAR]] -> 0
A73: 45916 | B73: 560000 | C73: =B73+(B73*F73/365*E73)*1 -> 591950.68 | D73: =+A73+E73 -> 45965 | E73: 49 | F73: 0.425 | G73: BBVA BANCO | H73: =(C73-B73)/E73*30 -> 19561.644 | I73: =VLOOKUP(Tabla1[[#This Row],[FECHA]],TablaUVA[#All],2) -> 1581.922 | J73: =VLOOKUP(Tabla1[[#This Row],[VTO.]],TablaUVA[#All],2) -> 1623.7965 | K73: =+Tabla1[[#This Row],[DEPOSITADO]]/I73 -> 353.99976 | L73: =IF(Tabla1[[#This Row],[DIAS]]>89,+K73*J73*(1+1%/365*Tabla1[[#This Row],[DIAS]]),Tabla1[[#This Row],[ACOBRAR]]) -> 591950.68 | M73: =+L73-Tabla1[[#This Row],[ACOBRAR]] -> 0
A74: 45922 | B74: 250000 | C74: =B74+(B74*F74/365*E74)*1 -> 261904.11 | D74: =+A74+E74 -> 45966 | E74: 44 | F74: 0.395 | G74: BBVA BANCO BARBARA | H74: =(C74-B74)/E74*30 -> 8116.4384 | I74: =VLOOKUP(Tabla1[[#This Row],[FECHA]],TablaUVA[#All],2) -> 1586.9909 | J74: =VLOOKUP(Tabla1[[#This Row],[VTO.]],TablaUVA[#All],2) -> 1624.6625 | K74: =+Tabla1[[#This Row],[DEPOSITADO]]/I74 -> 157.53084 | L74: =IF(Tabla1[[#This Row],[DIAS]]>89,+K74*J74*(1+1%/365*Tabla1[[#This Row],[DIAS]]),Tabla1[[#This Row],[ACOBRAR]]) -> 261904.11 | M74: =+L74-Tabla1[[#This Row],[ACOBRAR]] -> 0
A75: 45922 | B75: 638000 | C75: =B75+(B75*F75/365*E75)*1 -> 667225.64 | D75: =+A75+E75 -> 45966 | E75: 44 | F75: 0.38 | G75: BBVA BANCO RAMONA | H75: =(C75-B75)/E75*30 -> 19926.575 | I75: =VLOOKUP(Tabla1[[#This Row],[FECHA]],TablaUVA[#All],2) -> 1586.9909 | J75: =VLOOKUP(Tabla1[[#This Row],[VTO.]],TablaUVA[#All],2) -> 1624.6625 | K75: =+Tabla1[[#This Row],[DEPOSITADO]]/I75 -> 402.01869 | L75: =IF(Tabla1[[#This Row],[DIAS]]>89,+K75*J75*(1+1%/365*Tabla1[[#This Row],[DIAS]]),Tabla1[[#This Row],[ACOBRAR]]) -> 667225.64 | M75: =+L75-Tabla1[[#This Row],[ACOBRAR]] -> 0
... A81: 45922 | B81: 1105000 | C81: =B81+(B81*F81/365*E81)*1 -> 1164881.9 | D81: =+A81+E81 -> 45968 | E81: 46 | F81: 0.43 | G81: HSBC BANCO | H81: =(C81-B81)/E81*30 -> 39053.425 | I81: =VLOOKUP(Tabla1[[#This Row],[FECHA]],TablaUVA[#All],2) -> 1586.9909 | J81: =VLOOKUP(Tabla1[[#This Row],[VTO.]],TablaUVA[#All],2) -> 1626.3959 | K81: =+Tabla1[[#This Row],[DEPOSITADO]]/I81 -> 696.28629 | L81: =IF(Tabla1[[#This Row],[DIAS]]>89,+K81*J81*(1+1%/365*Tabla1[[#This Row],[DIAS]]),Tabla1[[#This Row],[ACOBRAR]]) -> 1164881.9 | M81: =+L81-Tabla1[[#This Row],[ACOBRAR]] -> 0
A82: 45922 | B82: 1047000 | C82: =B82+(B82*F82/365*E82)*1 -> 1107697.3 | D82: =+A82+E82 -> 45968 | E82: 46 | F82: 0.46 | G82: ITAU BANCO | H82: =(C82-B82)/E82*30 -> 39585.205 | I82: =VLOOKUP(Tabla1[[#This Row],[FECHA]],TablaUVA[#All],2) -> 1586.9909 | J82: =VLOOKUP(Tabla1[[#This Row],[VTO.]],TablaUVA[#All],2) -> 1626.3959 | K82: =+Tabla1[[#This Row],[DEPOSITADO]]/I82 -> 659.73914 | L82: =IF(Tabla1[[#This Row],[DIAS]]>89,+K82*J82*(1+1%/365*Tabla1[[#This Row],[DIAS]]),Tabla1[[#This Row],[ACOBRAR]]) -> 1107697.3 | M82: =+L82-Tabla1[[#This Row],[ACOBRAR]] -> 0 | N82: =SUM(#REF!) -> #REF! | O82: =SUM(#REF!) -> #REF! | P82: =+O82-N82 -> #REF!
A83: 45922 | B83: 399000 | C83: =B83+(B83*F83/365*E83)*1 -> 420622.52 | D83: =+A83+E83 -> 45968 | E83: 46 | F83: 0.43 | G83: BNA JUBIL. BANCO | H83: =(C83-B83)/E83*30 -> 14101.644 | I83: =VLOOKUP(Tabla1[[#This Row],[FECHA]],TablaUVA[#All],2) -> 1586.9909 | J83: =VLOOKUP(Tabla1[[#This Row],[VTO.]],TablaUVA[#All],2) -> 1626.3959 | K83: =+Tabla1[[#This Row],[DEPOSITADO]]/I83 -> 251.41921 | L83: =IF(Tabla1[[#This Row],[DIAS]]>89,+K83*J83*(1+1%/365*Tabla1[[#This Row],[DIAS]]),Tabla1[[#This Row],[ACOBRAR]]) -> 420622.52 | M83: =+L83-Tabla1[[#This Row],[ACOBRAR]] -> 0
A84: 45923 | B84: 1590000 | C84: =B84+(B84*F84/365*E84)*1 -> 1683047.7 | D84: =+A84+E84 -> 45971 | E84: 48 | F84: 0.445 | G84: HSBC BANCO | H84: =(C84-B84)/E84*30 -> 58154.795 | I84: =VLOOKUP(Tabla1[[#This Row],[FECHA]],TablaUVA[#All],2) -> 1587.8373 | J84: =VLOOKUP(Tabla1[[#This Row],[VTO.]],TablaUVA[#All],2) -> 1628.9996 | K84: =+Tabla1[[#This Row],[DEPOSITADO]]/I84 -> 1001.3621 | L84: =IF(Tabla1[[#This Row],[DIAS]]>89,+K84*J84*(1+1%/365*Tabla1[[#This Row],[DIAS]]),Tabla1[[#This Row],[ACOBRAR]]) -> 1683047.7 | M84: =+L84-Tabla1[[#This Row],[ACOBRAR]] -> 0
A85: 45923 | B85: 1557000 | C85: =B85+(B85*F85/365*E85)*1 -> 2498878.4 | D85: =+A85+E85 -> 45971 | E85: 48 | F85: 4.6 | G85: ITAU BANCO | H85: =(C85-B85)/E85*30 -> 588673.97 | I85: =VLOOKUP(Tabla1[[#This Row],[FECHA]],TablaUVA[#All],2) -> 1587.8373 | J85: =VLOOKUP(Tabla1[[#This Row],[VTO.]],TablaUVA[#All],2) -> 1628.9996 | K85: =+Tabla1[[#This Row],[DEPOSITADO]]/I85 -> 980.57907 | L85: =IF(Tabla1[[#This Row],[DIAS]]>89,+K85*J85*(1+1%/365*Tabla1[[#This Row],[DIAS]]),Tabla1[[#This Row],[ACOBRAR]]) -> 2498878.4 | M85: =+L85-Tabla1[[#This Row],[ACOBRAR]] -> 0
A86: 45924 | B86: 1000000 | C86: =B86+(B86*F86/365*E86)*1 -> 1054575.3 | D86: =+A86+E86 -> 45972 | E86: 48 | F86: 0.415 | G86: BBVA BANCO | H86: =(C86-B86)/E86*30 -> 34109.589 | I86: =VLOOKUP(Tabla1[[#This Row],[FECHA]],TablaUVA[#All],2) -> 1588.6841 | J86: =VLOOKUP(Tabla1[[#This Row],[VTO.]],TablaUVA[#All],2) -> 1629.8684 | K86: =+Tabla1[[#This Row],[DEPOSITADO]]/I86 -> 629.45175 | L86: =IF(Tabla1[[#This Row],[DIAS]]>89,+K86*J86*(1+1%/365*Tabla1[[#This Row],[DIAS]]),Tabla1[[#This Row],[ACOBRAR]]) -> 1054575.3 | M86: =+L86-Tabla1[[#This Row],[ACOBRAR]] -> 0
A87: 45924 | B87: 1000000 | C87: =B87+(B87*F87/365*E87)*1 -> 1052602.7 | D87: =+A87+E87 -> 45972 | E87: 48 | F87: 0.4 | G87: HSBC BANCO | H87: =(C87-B87)/E87*30 -> 32876.712 | I87: =VLOOKUP(Tabla1[[#This Row],[FECHA]],TablaUVA[#All],2) -> 1588.6841 | J87: =VLOOKUP(Tabla1[[#This Row],[VTO.]],TablaUVA[#All],2) -> 1629.8684 | K87: =+Tabla1[[#This Row],[DEPOSITADO]]/I87 -> 629.45175 | L87: =IF(Tabla1[[#This Row],[DIAS]]>89,+K87*J87*(1+1%/365*Tabla1[[#This Row],[DIAS]]),Tabla1[[#This Row],[ACOBRAR]]) -> 1052602.7 | M87: =+L87-Tabla1[[#This Row],[ACOBRAR]] -> 0
A88: 45924 | B88: 984000 | C88: =B88+(B88*F88/365*E88)*1 -> 1043525.3 | D88: =+A88+E88 -> 45972 | E88: 48 | F88: 0.46 | G88: ITAU BANCO | H88: =(C88-B88)/E88*30 -> 37203.288 | I88: =VLOOKUP(Tabla1[[#This Row],[FECHA]],TablaUVA[#All],2) -> 1588.6841 | J88: =VLOOKUP(Tabla1[[#This Row],[VTO.]],TablaUVA[#All],2) -> 1629.8684 | K88: =+Tabla1[[#This Row],[DEPOSITADO]]/I88 -> 619.38052 | L88: =IF(Tabla1[[#This Row],[DIAS]]>89,+K88*J88*(1+1%/365*Tabla1[[#This Row],[DIAS]]),Tabla1[[#This Row],[ACOBRAR]]) -> 1043525.3 | M88: =+L88-Tabla1[[#This Row],[ACOBRAR]] -> 0 | N88: =SUM(#REF!) -> #REF!
A89: 45926 | B89: 454000 | C89: =B89+(B89*F89/365*E89)*1 -> 475338 | D89: =+A89+E89 -> 45973 | E89: 47 | F89: 0.365 | G89: BBVA BANCO BARBARA | H89: =(C89-B89)/E89*30 -> 13620 | I89: =VLOOKUP(Tabla1[[#This Row],[FECHA]],TablaUVA[#All],2) -> 1590.3792 | J89: =VLOOKUP(Tabla1[[#This Row],[VTO.]],TablaUVA[#All],2) -> 1630.7376 | K89: =+Tabla1[[#This Row],[DEPOSITADO]]/I89 -> 285.46651 | L89: =IF(Tabla1[[#This Row],[DIAS]]>89,+K89*J89*(1+1%/365*Tabla1[[#This Row],[DIAS]]),Tabla1[[#This Row],[ACOBRAR]]) -> 475338 | M89: =+L89-Tabla1[[#This Row],[ACOBRAR]] -> 0
A90: 45925 | B90: 1000000 | C90: =B90+(B90*F90/365*E90)*1 -> 1048000 | D90: =+A90+E90 -> 45973 | E90: 48 | F90: 0.365 | G90: BBVA BANCO | H90: =(C90-B90)/E90*30 -> 30000 | I90: =VLOOKUP(Tabla1[[#This Row],[FECHA]],TablaUVA[#All],2) -> 1589.5314 | J90: =VLOOKUP(Tabla1[[#This Row],[VTO.]],TablaUVA[#All],2) -> 1630.7376 | K90: =+Tabla1[[#This Row],[DEPOSITADO]]/I90 -> 629.11622 | L90: =IF(Tabla1[[#This Row],[DIAS]]>89,+K90*J90*(1+1%/365*Tabla1[[#This Row],[DIAS]]),Tabla1[[#This Row],[ACOBRAR]]) -> 1048000 | M90: =+L90-Tabla1[[#This Row],[ACOBRAR]] -> 0
A91: 45925 | B91: 1000000 | C91: =B91+(B91*F91/365*E91)*1 -> 1048986.3 | D91: =+A91+E91 -> 45973 | E91: 48 | F91: 0.3725 | G91: HSBC BANCO | H91: =(C91-B91)/E91*30 -> 30616.438 | I91: =VLOOKUP(Tabla1[[#This Row],[FECHA]],TablaUVA[#All],2) -> 1589.5314 | J91: =VLOOKUP(Tabla1[[#This Row],[VTO.]],TablaUVA[#All],2) -> 1630.7376 | K91: =+Tabla1[[#This Row],[DEPOSITADO]]/I91 -> 629.11622 | L91: =IF(Tabla1[[#This Row],[DIAS]]>89,+K91*J91*(1+1%/365*Tabla1[[#This Row],[DIAS]]),Tabla1[[#This Row],[ACOBRAR]]) -> 1048986.3 | M91: =+L91-Tabla1[[#This Row],[ACOBRAR]] -> 0
A92: 45924 | B92: 550000 | C92: =B92+(B92*F92/365*E92)*1 -> 577503.77 | D92: =+A92+E92 -> 45973 | E92: 49 | F92: 0.3725 | G92: HSBC BANCO | H92: =(C92-B92)/E92*30 -> 16839.041 | I92: =VLOOKUP(Tabla1[[#This Row],[FECHA]],TablaUVA[#All],2) -> 1588.6841 | J92: =VLOOKUP(Tabla1[[#This Row],[VTO.]],TablaUVA[#All],2) -> 1630.7376 | K92: =+Tabla1[[#This Row],[DEPOSITADO]]/I92 -> 346.19846 | L92: =IF(Tabla1[[#This Row],[DIAS]]>89,+K92*J92*(1+1%/365*Tabla1[[#This Row],[DIAS]]),Tabla1[[#This Row],[ACOBRAR]]) -> 577503.77 | M92: =+L92-Tabla1[[#This Row],[ACOBRAR]] -> 0
A93: 45926 | B93: 599000 | C93: =B93+(B93*F93/365*E93)*1 -> 626570.41 | D93: =+A93+E93 -> 45974 | E93: 48 | F93: 0.35 | G93: BBVA BANCO RAMONA | H93: =(C93-B93)/E93*30 -> 17231.507 | I93: =VLOOKUP(Tabla1[[#This Row],[FECHA]],TablaUVA[#All],2) -> 1590.3792 | J93: =VLOOKUP(Tabla1[[#This Row],[VTO.]],TablaUVA[#All],2) -> 1631.6074 | K93: =+Tabla1[[#This Row],[DEPOSITADO]]/I93 -> 376.63974 | L93: =IF(Tabla1[[#This Row],[DIAS]]>89,+K93*J93*(1+1%/365*Tabla1[[#This Row],[DIAS]]),Tabla1[[#This Row],[ACOBRAR]]) -> 626570.41 | M93: =+L93-Tabla1[[#This Row],[ACOBRAR]] -> 0
A94: 45926 | B94: 1400000 | C94: =B94+(B94*F94/365*E94)*1 -> 1468580.8 | D94: =+A94+E94 -> 45974 | E94: 48 | F94: 0.3725 | G94: HSBC BANCO | H94: =(C94-B94)/E94*30 -> 42863.014 | I94: =VLOOKUP(Tabla1[[#This Row],[FECHA]],TablaUVA[#All],2) -> 1590.3792 | J94: =VLOOKUP(Tabla1[[#This Row],[VTO.]],TablaUVA[#All],2) -> 1631.6074 | K94: =+Tabla1[[#This Row],[DEPOSITADO]]/I94 -> 880.29322 | L94: =IF(Tabla1[[#This Row],[DIAS]]>89,+K94*J94*(1+1%/365*Tabla1[[#This Row],[DIAS]]),Tabla1[[#This Row],[ACOBRAR]]) -> 1468580.8 | M94: =+L94-Tabla1[[#This Row],[ACOBRAR]] -> 0
A95: 45925 | B95: 1000000 | C95: =B95+(B95*F95/365*E95)*1 -> 1050006.8 | D95: =+A95+E95 -> 45974 | E95: 49 | F95: 0.3725 | G95: HSBC BANCO MARIA | H95: =(C95-B95)/E95*30 -> 30616.438 | I95: =VLOOKUP(Tabla1[[#This Row],[FECHA]],TablaUVA[#All],2) -> 1589.5314 | J95: =VLOOKUP(Tabla1[[#This Row],[VTO.]],TablaUVA[#All],2) -> 1631.6074 | K95: =+Tabla1[[#This Row],[DEPOSITADO]]/I95 -> 629.11622 | L95: =IF(Tabla1[[#This Row],[DIAS]]>89,+K95*J95*(1+1%/365*Tabla1[[#This Row],[DIAS]]),Tabla1[[#This Row],[ACOBRAR]]) -> 1050006.8 | M95: =+L95-Tabla1[[#This Row],[ACOBRAR]] -> 0
A96: 45933 | B96: 450000 | C96: =B96+(B96*F96/365*E96)*1 -> 469288.36 | D96: =+A96+E96 -> 45975 | E96: 42 | F96: 0.3725 | G96: HSBC BANCO | H96: =('PF ANTERIORES $'!C4019-'PF ANTERIORES $'!B4019)/'PF ANTERIORES $'!E4019*30 -> 9372.3288 | I96: =VLOOKUP(Tabla1[[#This Row],[FECHA]],TablaUVA[#All],2) -> 1596.3261 | J96: =VLOOKUP(Tabla1[[#This Row],[VTO.]],TablaUVA[#All],2) -> 1632.4775 | K96: =+Tabla1[[#This Row],[DEPOSITADO]]/I96 -> 281.89729 | L96: =IF(Tabla1[[#This Row],[DIAS]]>89,+K96*J96*(1+1%/365*Tabla1[[#This Row],[DIAS]]),Tabla1[[#This Row],[ACOBRAR]]) -> 469288.36 | M96: =+'PF ANTERIORES $'!L4019-Tabla1[[#This Row],[ACOBRAR]] -> -159603.62
A97: 45933 | B97: 600000 | C97: =B97+(B97*F97/365*E97)*1 -> 625890.41 | D97: =+A97+E97 -> 45975 | E97: 42 | F97: 0.375 | G97: BNA BANCO | H97: =(C97-B97)/E97*30 -> 18493.151 | I97: =VLOOKUP(Tabla1[[#This Row],[FECHA]],TablaUVA[#All],2) -> 1596.3261 | J97: =VLOOKUP(Tabla1[[#This Row],[VTO.]],TablaUVA[#All],2) -> 1632.4775 | K97: =+Tabla1[[#This Row],[DEPOSITADO]]/I97 -> 375.86305 | L97: =IF(Tabla1[[#This Row],[DIAS]]>89,+K97*J97*(1+1%/365*Tabla1[[#This Row],[DIAS]]),Tabla1[[#This Row],[ACOBRAR]]) -> 625890.41 | M97: =+L97-Tabla1[[#This Row],[ACOBRAR]] -> 0
A98: 45929 | B98: 260000 | C98: =B98+(B98*F98/365*E98)*1 -> 272205.75 | D98: =+A98+E98 -> 45975 | E98: 46 | F98: 0.3725 | G98: HSBC BANCO | H98: =(C98-B98)/E98*30 -> 7960.274 | I98: =VLOOKUP(Tabla1[[#This Row],[FECHA]],TablaUVA[#All],2) -> 1592.9251 | J98: =VLOOKUP(Tabla1[[#This Row],[VTO.]],TablaUVA[#All],2) -> 1632.4775 | K98: =+Tabla1[[#This Row],[DEPOSITADO]]/I98 -> 163.22173 | L98: =IF(Tabla1[[#This Row],[DIAS]]>89,+K98*J98*(1+1%/365*Tabla1[[#This Row],[DIAS]]),Tabla1[[#This Row],[ACOBRAR]]) -> 272205.75 | M98: =+L98-Tabla1[[#This Row],[ACOBRAR]] -> 0
A99: 45929 | B99: 420000 | C99: =B99+(B99*F99/365*E99)*1 -> 439716.99 | D99: =+A99+E99 -> 45975 | E99: 46 | F99: 0.3725 | G99: HSBC BANCO | H99: =(C99-B99)/E99*30 -> 12858.904 | I99: =VLOOKUP(Tabla1[[#This Row],[FECHA]],TablaUVA[#All],2) -> 1592.9251 | J99: =VLOOKUP(Tabla1[[#This Row],[VTO.]],TablaUVA[#All],2) -> 1632.4775 | K99: =+Tabla1[[#This Row],[DEPOSITADO]]/I99 -> 263.66587 | L99: =IF(Tabla1[[#This Row],[DIAS]]>89,+K99*J99*(1+1%/365*Tabla1[[#This Row],[DIAS]]),Tabla1[[#This Row],[ACOBRAR]]) -> 439716.99 | M99: =+L99-Tabla1[[#This Row],[ACOBRAR]] -> 0
A100: 45929 | B100: 420000 | C100: =B100+(B100*F100/365*E100)*1 -> 439716.99 | D100: =+A100+E100 -> 45975 | E100: 46 | F100: 0.3725 | G100: HSBC BANCO MARIA | H100: =(C100-B100)/E100*30 -> 12858.904 | I100: =VLOOKUP(Tabla1[[#This Row],[FECHA]],TablaUVA[#All],2) -> 1592.9251 | J100: =VLOOKUP(Tabla1[[#This Row],[VTO.]],TablaUVA[#All],2) -> 1632.4775 | K100: =+Tabla1[[#This Row],[DEPOSITADO]]/I100 -> 263.66587 | L100: =IF(Tabla1[[#This Row],[DIAS]]>89,+K100*J100*(1+1%/365*Tabla1[[#This Row],[DIAS]]),Tabla1[[#This Row],[ACOBRAR]]) -> 439716.99 | M100: =+L100-Tabla1[[#This Row],[ACOBRAR]] -> 0
A101: 45929 | B101: 534000 | C101: =B101+(B101*F101/365*E101)*1 -> 559236.99 | D101: =+A101+E101 -> 45975 | E101: 46 | F101: 0.375 | G101: ITAU BANCO | H101: =(C101-B101)/E101*30 -> 16458.904 | I101: =VLOOKUP(Tabla1[[#This Row],[FECHA]],TablaUVA[#All],2) -> 1592.9251 | J101: =VLOOKUP(Tabla1[[#This Row],[VTO.]],TablaUVA[#All],2) -> 1632.4775 | K101: =+Tabla1[[#This Row],[DEPOSITADO]]/I101 -> 335.23233 | L101: =IF(Tabla1[[#This Row],[DIAS]]>89,+K101*J101*(1+1%/365*Tabla1[[#This Row],[DIAS]]),Tabla1[[#This Row],[ACOBRAR]]) -> 559236.99 | M101: =+L101-Tabla1[[#This Row],[ACOBRAR]] -> 0
A102: 45929 | B102: 229000 | C102: =B102+(B102*F102/365*E102)*1 -> 239389.7 | D102: =+A102+E102 -> 45975 | E102: 46 | F102: 0.36 | G102: BNA BANCO | H102: =(C102-B102)/E102*30 -> 6775.8904 | I102: =VLOOKUP(Tabla1[[#This Row],[FECHA]],TablaUVA[#All],2) -> 1592.9251 | J102: =VLOOKUP(Tabla1[[#This Row],[VTO.]],TablaUVA[#All],2) -> 1632.4775 | K102: =+Tabla1[[#This Row],[DEPOSITADO]]/I102 -> 143.76068 | L102: =IF(Tabla1[[#This Row],[DIAS]]>89,+K102*J102*(1+1%/365*Tabla1[[#This Row],[DIAS]]),Tabla1[[#This Row],[ACOBRAR]]) -> 239389.7 | M102: =+L102-Tabla1[[#This Row],[ACOBRAR]] -> 0
A103: 45946 | B103: 10000 | C103: =B103+(B103*F103/365*E103)*1 -> 10021.918 | D103: =+A103+E103 -> 45978 | E103: 32 | F103: 0.025 | G103: HSBC BANCO | H103: DOLARES | I103: =VLOOKUP(Tabla1[[#This Row],[FECHA]],TablaUVA[#All],2) -> 1607.4294 | J103: =VLOOKUP(Tabla1[[#This Row],[VTO.]],TablaUVA[#All],2) -> 1635.0909 | K103: =+Tabla1[[#This Row],[DEPOSITADO]]/I103 -> 6.2211129 | L103: =IF(Tabla1[[#This Row],[DIAS]]>89,+K103*J103*(1+1%/365*Tabla1[[#This Row],[DIAS]]),Tabla1[[#This Row],[ACOBRAR]]) -> 10021.918 | M103: =+L103-Tabla1[[#This Row],[ACOBRAR]] -> 0
A104: 45936 | B104: 950000 | C104: =B104+(B104*F104/365*E104)*1 -> 993179.45 | D104: =+A104+E104 -> 45978 | E104: 42 | F104: 0.395 | G104: ITAU BANCO | H104: =(C104-B104)/E104*30 -> 30842.466 | I104: =VLOOKUP(Tabla1[[#This Row],[FECHA]],TablaUVA[#All],2) -> 1598.8816 | J104: =VLOOKUP(Tabla1[[#This Row],[VTO.]],TablaUVA[#All],2) -> 1635.0909 | K104: =+Tabla1[[#This Row],[DEPOSITADO]]/I104 -> 594.16533 | L104: =IF(Tabla1[[#This Row],[DIAS]]>89,+K104*J104*(1+1%/365*Tabla1[[#This Row],[DIAS]]),Tabla1[[#This Row],[ACOBRAR]]) -> 993179.45 | M104: =+L104-Tabla1[[#This Row],[ACOBRAR]] -> 0
A105: 45933 | B105: 1200000 | C105: =B105+(B105*F105/365*E105)*1 -> 1255109.6 | D105: =+A105+E105 -> 45978 | E105: 45 | F105: 0.3725 | G105: HSBC BANCO | H105: =('PF ANTERIORES $'!C4020-'PF ANTERIORES $'!B4020)/'PF ANTERIORES $'!E4020*30 -> 25879.008 | I105: =VLOOKUP(Tabla1[[#This Row],[FECHA]],TablaUVA[#All],2) -> 1596.3261 | J105: =VLOOKUP(Tabla1[[#This Row],[VTO.]],TablaUVA[#All],2) -> 1635.0909 | K105: =+Tabla1[[#This Row],[DEPOSITADO]]/I105 -> 751.7261 | L105: =IF(Tabla1[[#This Row],[DIAS]]>89,+K105*J105*(1+1%/365*Tabla1[[#This Row],[DIAS]]),Tabla1[[#This Row],[ACOBRAR]]) -> 1255109.6 | M105: =+'PF ANTERIORES $'!L4020-Tabla1[[#This Row],[ACOBRAR]] -> -924835.54
A106: 45933 | B106: 783000 | C106: =B106+(B106*F106/365*E106)*1 -> 819200.34 | D106: =+A106+E106 -> 45978 | E106: 45 | F106: 0.375 | G106: BNA BANCO | H106: =(C106-B106)/E106*30 -> 24133.562 | I106: =VLOOKUP(Tabla1[[#This Row],[FECHA]],TablaUVA[#All],2) -> 1596.3261 | J106: =VLOOKUP(Tabla1[[#This Row],[VTO.]],TablaUVA[#All],2) -> 1635.0909 | K106: =+Tabla1[[#This Row],[DEPOSITADO]]/I106 -> 490.50128 | L106: =IF(Tabla1[[#This Row],[DIAS]]>89,+K106*J106*(1+1%/365*Tabla1[[#This Row],[DIAS]]),Tabla1[[#This Row],[ACOBRAR]]) -> 819200.34 | M106: =+L106-Tabla1[[#This Row],[ACOBRAR]] -> 0 | N106: =SUM(#REF!) -> #REF!
A107: 45938 | B107: 455000 | C107: =B107+(B107*F107/365*E107)*1 -> 474677.19 | D107: =+A107+E107 -> 45979 | E107: 41 | F107: 0.385 | G107: BBVA BANCO RAMONA | H107: =(C107-B107)/E107*30 -> 14397.945 | I107: =VLOOKUP(Tabla1[[#This Row],[FECHA]],TablaUVA[#All],2) -> 1600.5875 | J107: =VLOOKUP(Tabla1[[#This Row],[VTO.]],TablaUVA[#All],2) -> 1635.963 | K107: =+Tabla1[[#This Row],[DEPOSITADO]]/I107 -> 284.27062 | L107: =IF(Tabla1[[#This Row],[DIAS]]>89,+K107*J107*(1+1%/365*Tabla1[[#This Row],[DIAS]]),Tabla1[[#This Row],[ACOBRAR]]) -> 474677.19 | M107: =+L107-Tabla1[[#This Row],[ACOBRAR]] -> 0
A108: 45937 | B108: 900000 | C108: =B108+(B108*F108/365*E108)*1 -> 940906.85 | D108: =+A108+E108 -> 45979 | E108: 42 | F108: 0.395 | G108: HSBC BANCO | H108: =(C108-B108)/E108*30 -> 29219.178 | I108: =VLOOKUP(Tabla1[[#This Row],[FECHA]],TablaUVA[#All],2) -> 1599.7343 | J108: =VLOOKUP(Tabla1[[#This Row],[VTO.]],TablaUVA[#All],2) -> 1635.963 | K108: =+Tabla1[[#This Row],[DEPOSITADO]]/I108 -> 562.59342 | L108: =IF(Tabla1[[#This Row],[DIAS]]>89,+K108*J108*(1+1%/365*Tabla1[[#This Row],[DIAS]]),Tabla1[[#This Row],[ACOBRAR]]) -> 940906.85 | M108: =+L108-Tabla1[[#This Row],[ACOBRAR]] -> 0
A109: 45936 | B109: 1590000 | C109: =B109+(B109*F109/365*E109)*1 -> 1663989.5 | D109: =+A109+E109 -> 45979 | E109: 43 | F109: 0.395 | G109: ITAU BANCO | H109: =(C109-B109)/E109*30 -> 51620.548 | I109: =VLOOKUP(Tabla1[[#This Row],[FECHA]],TablaUVA[#All],2) -> 1598.8816 | J109: =VLOOKUP(Tabla1[[#This Row],[VTO.]],TablaUVA[#All],2) -> 1635.963 | K109: =+Tabla1[[#This Row],[DEPOSITADO]]/I109 -> 994.44513 | L109: =IF(Tabla1[[#This Row],[DIAS]]>89,+K109*J109*(1+1%/365*Tabla1[[#This Row],[DIAS]]),Tabla1[[#This Row],[ACOBRAR]]) -> 1663989.5 | M109: =+L109-Tabla1[[#This Row],[ACOBRAR]] -> 0
A110: 45939 | B110: 528000 | C110: =B110+(B110*F110/365*E110)*1 -> 551130.74 | D110: =+A110+E110 -> 45980 | E110: 41 | F110: 0.39 | G110: BNA JUBIL. BANCO | H110: =(C110-B110)/E110*30 -> 16924.932 | I110: =VLOOKUP(Tabla1[[#This Row],[FECHA]],TablaUVA[#All],2) -> 1601.4412 | J110: =VLOOKUP(Tabla1[[#This Row],[VTO.]],TablaUVA[#All],2) -> 1636.8355 | K110: =+Tabla1[[#This Row],[DEPOSITADO]]/I110 -> 329.70303 | L110: =IF(Tabla1[[#This Row],[DIAS]]>89,+K110*J110*(1+1%/365*Tabla1[[#This Row],[DIAS]]),Tabla1[[#This Row],[ACOBRAR]]) -> 551130.74 | M110: =+L110-Tabla1[[#This Row],[ACOBRAR]] -> 0
A111: 45938 | B111: 430000 | C111: =B111+(B111*F111/365*E111)*1 -> 450781.37 | D111: =+A111+E111 -> 45980 | E111: 42 | F111: 0.42 | G111: HSBC BANCO | H111: =(C111-B111)/E111*30 -> 14843.836 | I111: =VLOOKUP(Tabla1[[#This Row],[FECHA]],TablaUVA[#All],2) -> 1600.5875 | J111: =VLOOKUP(Tabla1[[#This Row],[VTO.]],TablaUVA[#All],2) -> 1636.8355 | K111: =+Tabla1[[#This Row],[DEPOSITADO]]/I111 -> 268.65135 | L111: =IF(Tabla1[[#This Row],[DIAS]]>89,+K111*J111*(1+1%/365*Tabla1[[#This Row],[DIAS]]),Tabla1[[#This Row],[ACOBRAR]]) -> 450781.37 | M111: =+L111-Tabla1[[#This Row],[ACOBRAR]] -> 0 | N111: =SUM(#REF!) -> #REF!
A112: 45938 | B112: 430000 | C112: =B112+(B112*F112/365*E112)*1 -> 450781.37 | D112: =+A112+E112 -> 45980 | E112: 42 | F112: 0.42 | G112: HSBC BANCO MARIA | H112: =(C112-B112)/E112*30 -> 14843.836 | I112: =VLOOKUP(Tabla1[[#This Row],[FECHA]],TablaUVA[#All],2) -> 1600.5875 | J112: =VLOOKUP(Tabla1[[#This Row],[VTO.]],TablaUVA[#All],2) -> 1636.8355 | K112: =+Tabla1[[#This Row],[DEPOSITADO]]/I112 -> 268.65135 | L112: =IF(Tabla1[[#This Row],[DIAS]]>89,+K112*J112*(1+1%/365*Tabla1[[#This Row],[DIAS]]),Tabla1[[#This Row],[ACOBRAR]]) -> 450781.37 | M112: =+L112-Tabla1[[#This Row],[ACOBRAR]] -> 0 | N112: =SUM(#REF!) -> #REF!
A113: 45938 | B113: 890000 | C113: =B113+(B113*F113/365*E113)*1 -> 942229.59 | D113: =+A113+E113 -> 45980 | E113: 42 | F113: 0.51 | G113: HSBC BANCO | H113: =(C113-B113)/E113*30 -> 37306.849 | I113: =VLOOKUP(Tabla1[[#This Row],[FECHA]],TablaUVA[#All],2) -> 1600.5875 | J113: =VLOOKUP(Tabla1[[#This Row],[VTO.]],TablaUVA[#All],2) -> 1636.8355 | K113: =+Tabla1[[#This Row],[DEPOSITADO]]/I113 -> 556.04582 | L113: =IF(Tabla1[[#This Row],[DIAS]]>89,+K113*J113*(1+1%/365*Tabla1[[#This Row],[DIAS]]),Tabla1[[#This Row],[ACOBRAR]]) -> 942229.59 | M113: =+L113-Tabla1[[#This Row],[ACOBRAR]] -> 0
A114: 45937 | B114: 488000 | C114: =B114+(B114*F114/365*E114)*1 -> 510708.71 | D114: =+A114+E114 -> 45980 | E114: 43 | F114: 0.395 | G114: ITAU BANCO | H114: =(C114-B114)/E114*30 -> 15843.288 | I114: =VLOOKUP(Tabla1[[#This Row],[FECHA]],TablaUVA[#All],2) -> 1599.7343 | J114: =VLOOKUP(Tabla1[[#This Row],[VTO.]],TablaUVA[#All],2) -> 1636.8355 | K114: =+Tabla1[[#This Row],[DEPOSITADO]]/I114 -> 305.05065 | L114: =IF(Tabla1[[#This Row],[DIAS]]>89,+K114*J114*(1+1%/365*Tabla1[[#This Row],[DIAS]]),Tabla1[[#This Row],[ACOBRAR]]) -> 510708.71 | M114: =+L114-Tabla1[[#This Row],[ACOBRAR]] -> 0 | N114: =SUM(#REF!) -> #REF!
...

Sheet POR VTO.
A11: Etiquetas de fila | B11: Suma de ACOBRAR
A12: 45964 | B12: 3602793.5
A13: 45965 | B13: 3156535.2
A14: 45966 | B14: 3266257.6
A15: 45968 | B15: 3113321.6
A16: 45971 | B16: 4181926
A17: 45972 | B17: 3150703.3
A18: 45973 | B18: 3149828.1
A19: 45974 | B19: 3145158.1
A20: 45975 | B20: 3045445.2
A21: 45978 | B21: 3077511.3
A22: 45979 | B22: 3079573.5
A23: 45980 | B23: 3460294.9
... A41: 46034 | B41: 1041356.2
A42: Total general | B42: 92288676
B52: 1534
B53: -150
B54: =+B52+B53 -> 1384
B55: -700
B56: =+B54+B55 -> 684

Sheet PF ANTERIORES $
A1: Fecha | B1: Depositado | C1: A Cobrar | D1: Fecha Vto. | E1: Dias | F1: Tasa
A2: 34774 | B2: 600 | C2: =B2+(B2*F2/365*E2)*1 -> 632.68997 | D2: =A2+E2 -> 34810 | E2: 36 | F2: 0.5524 | G2: BID
A3: 34774 | B3: 849 | C3: =B3+(B3*F3/365*E3)*1 -> 895.25631 | D3: =A3+E3 -> 34810 | E3: 36 | F3: 0.5524 | G3: BID
A4: 34768 | B4: 1440 | C4: =B4+(B4*F4/365*E4)*1 -> 1521.2752 | D4: =A4+E4 -> 34810 | E4: 42 | F4: 0.4905 | G4: BID
A5: 34775 | B5: 522 | C5: =B5+(B5*F5/365*E5)*1 -> 549.63025 | D5: =A5+E5 -> 34810 | E5: 35 | F5: 0.552 | G5: BID
A6: 34772 | B6: 2105 | C6: =B6+(B6*F6/365*E6)*1 -> 2226.2342 | D6: =A6+E6 -> 34810 | E6: 38 | F6: 0.5532 | G6: BID
A7: 34778 | B7: 700 | C7: =B7+(B7*F7/365*E7)*1 -> 733.80252 | D7: =A7+E7 -> 34810 | E7: 32 | F7: 0.5508 | G7: BID
A8: 34773 | B8: 1739 | C8: =B8+(B8*F8/365*E8)*1 -> 1836.4488 | D8: =A8+E8 -> 34810 | E8: 37 | F8: 0.5528 | G8: BID
A9: 34767 | B9: 2095 | C9: =B9+(B9*F9/365*E9)*1 -> 2216.1582 | D9: =A9+E9 -> 34810 | E9: 43 | F9: 0.4909 | G9: BID
A10: 34771 | B10: 668 | C10: =B10+(B10*F10/365*E10)*1 -> 707.51339 | D10: =A10+E10 -> 34810 | E10: 39 | F10: 0.5536 | G10: BID
A11: 34775 | B11: 25833.04 | C11: =B11+(B11*F11/365*E11)*1 -> 27361.11 | D11: =A11+E11 -> 34814 | E11: 39 | F11: 0.5536 | G11: BID
A12: 34782 | B12: 407 | C12: =B12+(B12*F12/365*E12)*1 -> 426.05708 | D12: =A12+E12 -> 34817 | E12: 35 | F12: 0.4883 | G12: BID
A13: 34787 | B13: 2170 | C13: =B13+(B13*F13/365*E13)*1 -> 2256.8059 | D13: =A13+E13 -> 34817 | E13: 30 | F13: 0.4867 | G13: BID
... A25: 34801 | B25: 2445 | C25: =B25+(B25*F25/365*E25)*1 -> 2542.8067 | D25: =A25+E25 -> 34831 | E25: 30 | F25: 0.4867 | G25: BID
B26: =SUM(B2:B25) -> 114521.26 | C26: =SUM(C2:C25) -> 120211.17
A27: Fecha | B27: Depositado | C27: A Cobrar | D27: Fecha Vto. | E27: Dias | F27: Tasa
A28: 34837 | B28: 10000 | C28: =B28+(B28*F28/365*E28)*1 -> 10198.904 | D28: =A28+E28 -> 34870 | E28: 33 | F28: 0.22 | G28: MERCANTIL
A29: 34837 | B29: 10000 | C29: =B29+(B29*F29/365*E29)*1 -> 10198.904 | D29: =A29+E29 -> 34870 | E29: 33 | F29: 0.22 | G29: MERCANTIL
A30: 34841 | B30: 9000 | C30: =B30+(B30*F30/365*E30)*1 -> 9103.5616 | D30: =A30+E30 -> 34871 | E30: 30 | F30: 0.14 | G30: BNL
A31: 34841 | B31: 8494.94 | C31: =B31+(B31*F31/365*E31)*1 -> 8592.69 | D31: =A31+E31 -> 34871 | E31: 30 | F31: 0.14 | G31: BNL
A32: 34841 | B32: 10000 | C32: =B32+(B32*F32/365*E32)*1 -> 10156.164 | D32: =A32+E32 -> 34871 | E32: 30 | F32: 0.19 | G32: MERCANTIL
A33: 34841 | B33: 10000 | C33: =B33+(B33*F33/365*E33)*1 -> 10156.164 | D33: =A33+E33 -> 34871 | E33: 30 | F33: 0.19 | G33: MERCANTIL
A34: 34837 | B34: 10000 | C34: =B34+(B34*F34/365*E34)*1 -> 10240.46 | D34: =A34+E34 -> 34873 | E34: 36 | F34: 0.2438 | G34: SUDECOR
A35: 34843 | B35: 10000 | C35: =B35+(B35*F35/365*E35)*1 -> 10189.041 | D35: =A35+E35 -> 34873 | E35: 30 | F35: 0.23 | G35: BUEN AYRE
A36: 34837 | B36: 10000 | C36: =B36+(B36*F36/365*E36)*1 -> 10240.46 | D36: =A36+E36 -> 34873 | E36: 36 | F36: 0.2438 | G36: SUDECOR
A37: 34843 | B37: 39960 | C37: =B37+(B37*F37/365*E37)*1 -> 40584.033 | D37: =A37+E37 -> 34873 | E37: 30 | F37: 0.19 | G37: MERCANTIL
A38: 34843 | B38: 20000 | C38: =B38+(B38*F38/365*E38)*1 -> 20515.068 | D38: =A38+E38 -> 34883 | E38: 40 | F38: 0.235 | G38: BUEN AYRE
A39: 34851 | B39: 7179 | C39: =B39+(B39*F39/365*E39)*1 -> 7336.3479 | D39: =A39+E39 -> 34891 | E39: 40 | F39: 0.2 | G39: BUEN AYRE
... A119: 35125 | B119: 2500 | C119: =B119+(B119*F119/365*E119)*1 -> 2532.8767 | D119: =A119+E119 -> 35165 | E119: 40 | F119: 0.12 | G119: SUDECOR
A120: 35116 | B120: =44324.49+2000 -> 46324.49 | C120: =B120+(B120*F120/365*E120)*1 -> 46946.38 | D120: =A120+E120 -> 35165 | E120: 49 | F120: 0.1 | G120: MERCANTIL
A121: 35123 | B121: 16336.92 | C121: =B121+(B121*F121/365*E121)*1 -> 16562.504 | D121: =A121+E121 -> 35165 | E121: 42 | F121: 0.12 | G121: SUDECOR
A122: 35123 | B122: 6650 | C122: =B122+(B122*F122/365*E122)*1 -> 6734.8103 | D122: =A122+E122 -> 35172 | E122: 49 | F122: 0.095 | G122: MERCANTIL
A123: 35123 | B123: 40506.3 | C123: =B123+(B123*F123/365*E123)*1 -> 41022.894 | D123: =A123+E123 -> 35172 | E123: 49 | F123: 0.095 | G123: MERCANTIL
A124: 35129 | B124: 3300 | C124: =B124+(B124*F124/365*E124)*1 -> 3336.9329 | D124: =A124+E124 -> 35172 | E124: 43 | F124: 0.095 | G124: MERCANTIL
A125: 35142 | B125: 19900 | C125: =B125+(B125*F125/365*E125)*1 -> 20119.881 | D125: =A125+E125 -> 35179 | E125: 37 | F125: 0.109 | G125: SUDECOR
A126: 35145 | B126: 10000 | C126: =B126+(B126*F126/365*E126)*1 -> 10119.452 | D126: =A126+E126 -> 35185 | E126: 40 | F126: 0.109 | G126: SUDECOR
A127: 35153 | B127: 25000 | C127: =B127+(B127*F127/365*E127)*1 -> 25238.904 | D127: =A127+E127 -> 35185 | E127: 32 | F127: 0.109 | G127: SUDECOR
A128: 35158 | B128: 28810 | C128: =B128+(B128*F128/365*E128)*1 -> 29058.634 | D128: =A128+E128 -> 35193 | E128: 35 | F128: 0.09 | G128: MERCANTIL
A129: 35158 | B129: 6000 | C129: =B129+(B129*F129/365*E129)*1 -> 6036.8219 | D129: =A129+E129 -> 35193 | E129: 35 | F129: 0.064 | G129: BNL
A130: 35165 | B130: 32305.35 | C130: =B130+(B130*F130/365*E130)*1 -> 32641.149 | D130: =A130+E130 -> 35200 | E130: 35 | F130: 0.1084 | G130: SUDECOR
A131: 35174 | B131: 7190 | C131: =B131+(B131*F131/365*E131)*1 -> 7258.0607 | D131: =A131+E131 -> 35207 | E131: 33 | F131: 0.1047 | G131: SUDECOR
A132: 35165 | B132: 46946.38 | C132: =B132+(B132*F132/365*E132)*1 -> 47416.487 | D132: =A132+E132 -> 35208 | E132: 43 | F132: 0.085 | G132: MERCANTIL
... A160: 35312 | B160: 27831.73 | C160: =B160+(B160*F160/365*E160)*1 -> 28151.986 | D160: =A160+E160 -> 35347 | E160: 35 | F160: 0.12 | G160: BCPMAR
A161: 35314 | B161: 30000 | C161: =B161+(B161*F161/365*E161)*1 -> 30169.521 | D161: =A161+E161 -> 35347 | E161: 33 | F161: 0.0625
A162: 35319 | B162: 53000 | C162: =B162+(B162*F162/365*E162)*1 -> 53317.637 | D162: =A162+E162 -> 35354 | E162: 35 | F162: 0.0625
A163: 35320 | B163: 56000 | C163: =B163+(B163*F163/365*E163)*1 -> 56326.027 | D163: =A163+E163 -> 35354 | E163: 34 | F163: 0.0625
A164: 35327 | B164: 74000 | C164: =B164+(B164*F164/365*E164)*1 -> 74568.685 | D164: =A164+E164 -> 35360 | E164: 33 | F164: 0.085
A165: 35339 | B165: 20600 | C165: =B165+(B165*F165/365*E165)*1 -> 20705.822 | D165: =A165+E165 -> 35369 | E165: 30 | F165: 0.0625
A166: 35347 | B166: 28151.98 | C166: =B166+(B166*F166/365*E166)*1 -> 28475.921 | D166: =A166+E166 -> 35382 | E166: 35 | F166: 0.12 | G166: BCPMAR
A167: 35348 | B167: 38500 | C167: =B167+(B167*F167/365*E167)*1 -> 38930.356 | D167: =A167+E167 -> 35382 | E167: 34 | F167: 0.12 | G167: BCPMAR
A168: 35359 | B168: 21650 | C168: =B168+(B168*F168/365*E168)*1 -> 21863.534 | D168: =A168+E168 -> 35389 | E168: 30 | F168: 0.12 | G168: BCPMAR
A169: 35361 | B169: 74568.68 | C169: =B169+(B169*F169/365*E169)*1 -> 75013.028 | D169: =A169+E169 -> 35391 | E169: 30 | F169: 0.0725
A170: 35370 | B170: 47000 | C170: =B170+(B170*F170/365*E170)*1 -> 47479.014 | D170: =A170+E170 -> 35401 | E170: 31 | F170: 0.12 | G170: MAYO
A171: 35382 | B171: 28475.92 | C171: =B171+(B171*F171/365*E171)*1 -> 28745.076 | D171: =A171+E171 -> 35412 | E171: 30 | F171: 0.115 | G171: BCPMAR
A172: 35382 | B172: 38930.36 | C172: =B172+(B172*F172/365*E172)*1 -> 39298.332 | D172: =A172+E172 -> 35412 | E172: 30 | F172: 0.115 | G172: BCPMAR
A173: 35389 | B173: 21854.63 | C173: =B173+(B173*F173/365*E173)*1 -> 22061.201 | D173: =A173+E173 -> 35419 | E173: 30 | F173: 0.115 | G173: BCPMAR
A174: 35391 | B174: 32000 | C174: =B174+(B174*F174/365*E174)*1 -> 32285.37 | D174: =A174+E174 -> 35422 | E174: 31 | F174: 0.105 | G174: MAYO
A175: 35392 | B175: 40000 | C175: =B175+(B175*F175/365*E175)*1 -> 40390.685 | D175: =A175+E175 -> 35423 | E175: 31 | F175: 0.115 | G175: BCPMAR
A176: 35401 | B176: 47479.01 | C176: =B176+(B176*F176/365*E176)*1 -> 47984.369 | D176: =A176+E176 -> 35438 | E176: 37 | F176: 0.105 | G176: MAYO
A177: 35412 | B177: 28000 | C177: =B177+(B177*F177/365*E177)*1 -> 28265.808 | D177: =A177+E177 -> 35445 | E177: 33 | F177: 0.105 | G177: MAYO
A178: 35412 | B178: 28745.08 | C178: =B178+(B178*F178/365*E178)*1 -> 29043.95 | D178: =A178+E178 -> 35445 | E178: 33 | F178: 0.115 | G178: BCPMAR
A179: 35412 | B179: 39298.33 | C179: =B179+(B179*F179/365*E179)*1 -> 39706.925 | D179: =A179+E179 -> 35445 | E179: 33 | F179: 0.115 | G179: BCPMAR
A180: 35419 | B180: 22061.2 | C180: =B180+(B180*F180/365*E180)*1 -> 22290.576 | D180: =A180+E180 -> 35452 | E180: 33 | F180: 0.115 | G180: BCPMAR
A181: 35423 | B181: 40403.28 | C181: =B181+(B181*F181/365*E181)*1 -> 40861.553 | D181: =A181+E181 -> 35459 | E181: 36 | F181: 0.115 | G181: BCPMAR
... A190: 35464 | B190: 58321 | C190: =B190+(B190*F190/365*E190)*1 -> 58800.351 | D190: =A190+E190 -> 35494 | E190: 30 | F190: 0.1 | G190: MAYO
A191: 35466 | B191: =23197.71+5500 -> 28697.71 | C191: =B191+(B191*F191/365*E191)*1 -> 29014.171 | D191: =A191+E191 -> 35501 | E191: 35 | F191: 0.115 | G191: BCPMAR
A192: 35495 | B192: 64000 | C192: =B192+(B192*F192/365*E192)*1 -> 64073.644 | D192: =A192+E192 -> 35502 | E192: 7 | F192: 0.06 | G192: MAYOCAJA
A193: 35468 | B193: =55000*0.999 -> 54945 | C193: =B193+(B193*F193/365*E193)*1 -> 55637.458 | D193: =A193+E193 -> 35508 | E193: 40 | F193: 0.115 | G193: BCPMAR
A194: 35502 | B194: =64000+19000 -> 83000 | C194: =B194+(B194*F194/365*E194)*1 -> 83095.507 | D194: =A194+E194 -> 35509 | E194: 7 | F194: 0.06 | G194: MAYOCAJA
A195: 35475 | B195: 20432.18 | C195: =B195+(B195*F195/365*E195)*1 -> 20644.899 | D195: =A195+E195 -> 35515 | E195: 40 | F195: 0.095 | G195: MAYO
A196: 35475 | B196: 45082.22 | C196: =B196+(B196*F196/365*E196)*1 -> 45650.379 | D196: =A196+E196 -> 35515 | E196: 40 | F196: 0.115 | G196: BCPMAR
A197: 35475 | B197: 34318.45 | C197: =B197+(B197*F197/365*E197)*1 -> 34750.956 | D197: =A197+E197 -> 35515 | E197: 40 | F197: 0.115 | G197: BCPMAR
A198: 35515 | B198: =20644+3600 -> 24244 | C198: =B198+(B198*F198/365*E198)*1 -> 24271.897 | D198: =A198+E198 -> 35522 | E198: 7 | F198: 0.06 | G198: MAYOCAJA
A199: 35489 | B199: 12828.77 | C199: =B199+(B199*F199/365*E199)*1 -> 12938.957 | D199: =A199+E199 -> 35522 | E199: 33 | F199: 0.095 | G199: MAYO
A200: 35501 | B200: 29014.17 | C200: =B200+(B200*F200/365*E200)*1 -> 29334.121 | D200: =A200+E200 -> 35536 | E200: 35 | F200: 0.115 | G200: BCPMAR
A201: 35508 | B201: 55637.45 | C201: =B201+(B201*F201/365*E201)*1 -> 56250.986 | D201: =A201+E201 -> 35543 | E201: 35 | F201: 0.115 | G201: BCPMAR
A202: 35510 | B202: 56000 | C202: =B202+(B202*F202/365*E202)*1 -> 56521.644 | D202: =A202+E202 -> 35544 | E202: 34 | F202: 0.1 | G202: MAYO
A203: 35515 | B203: 45650.38 | C203: =B203+(B203*F203/365*E203)*1 -> 46153.785 | D203: =A203+E203 -> 35550 | E203: 35 | F203: 0.115 | G203: BCPMAR
A204: 35515 | B204: 34750.96 | C204: =B204+(B204*F204/365*E204)*1 -> 35134.173 | D204: =A204+E204 -> 35550 | E204: 35 | F204: 0.115 | G204: BCPMAR
A205: 35522 | B205: 45038.96 | C205: =B205+(B205*F205/365*E205)*1 -> 45470.84 | D205: =A205+E205 -> 35557 | E205: 35 | F205: 0.1 | G205: MAYO
A206: 35529 | B206: 88000 | C206: =B206+(B206*F206/365*E206)*1 -> 88843.836 | D206: =A206+E206 -> 35564 | E206: 35 | F206: 0.1 | G206: MAYO
A207: 35530 | B207: 49000 | C207: =B207+(B207*F207/365*E207)*1 -> 49550.411 | D207: =A207+E207 -> 35571 | E207: 41 | F207: 0.1 | G207: MAYO
A208: 35538 | B208: 5500 | C208: =B208+(B208*F208/365*E208)*1 -> 5549.726 | D208: =A208+E208 -> 35571 | E208: 33 | F208: 0.1 | G208: MAYO
A209: 35536 | B209: 29334.12 | C209: =B209+(B209*F209/365*E209)*1 -> 29671.663 | D209: =A209+E209 -> 35578 | E209: 42 | F209: 0.1 | G209: BCP
A210: 35545 | B210: 14000 | C210: =B210+(B210*F210/365*E210)*1 -> 14138.082 | D210: =A210+E210 -> 35585 | E210: 40 | F210: 0.09 | G210: MAYO
... A217: 35564 | B217: 68843.8 | C217: =B217+(B217*F217/365*E217)*1 -> 69768.004 | D217: =A217+E217 -> 35613 | E217: 49 | F217: 0.1 | G217: MAYO
A218: 35571 | B218: =49550.41+5549.73+3500 -> 58600.14 | C218: =B218+(B218*F218/365*E218)*1 -> 59402.882 | D218: =A218+E218 -> 35621 | E218: 50 | F218: 0.1 | G218: MAYO
A219: 35584 | B219: =9900+2000+4500 -> 16400 | C219: =B219+(B219*F219/365*E219)*1 -> 16566.247 | D219: =A219+E219 -> 35621 | E219: 37 | F219: 0.1 | G219: MAYO
A220: 35578 | B220: =29671.66+3000 -> 32671.66 | C220: =B220+(B220*F220/365*E220)*1 -> 33110.266 | D220: =A220+E220 -> 35627 | E220: 49 | F220: 0.1 | G220: BCP
A221: 35580 | B221: 30000 | C221: =B221+(B221*F221/365*E221)*1 -> 30386.301 | D221: =A221+E221 -> 35627 | E221: 47 | F221: 0.1 | G221: MAYO
A222: 35585 | B222: 20590.159 | C222: 20838.933 | D222: =A222+E222 -> 35634 | E222: 49 | F222: 0.09 | G222: MAYO
A223: 35599 | B223: 3500 | C223: =B223+(B223*F223/365*E223)*1 -> 3533.5616 | D223: =A223+E223 -> 35634 | E223: 35 | F223: 0.1 | G223: MAYO
A224: 35592 | B224: 63901.83 | C224: =B224+(B224*F224/365*E224)*1 -> 64738.244 | D224: =A224+E224 -> 35641 | E224: 49 | F224: 0.0975 | G224: BCP
A225: 35599 | B225: 46773.37 | C225: =B225+(B225*F225/365*E225)*1 -> 47385.589 | D225: =A225+E225 -> 35648 | E225: 49 | F225: 0.0975 | G225: BCP
A226: 35599 | B226: 35605.02 | C226: =B226+(B226*F226/365*E226)*1 -> 36071.056 | D226: =A226+E226 -> 35648 | E226: 49 | F226: 0.0975 | G226: BCP
A227: 35606 | B227: 63163.63 | C227: =B227+(B227*F227/365*E227)*1 -> 64011.58 | D227: =A227+E227 -> 35655 | E227: 49 | F227: 0.1 | G227: MAYO
A228: 35608 | B228: 3500 | C228: =B228+(B228*F228/365*E228)*1 -> 3540.5616 | D228: =A228+E228 -> 35655 | E228: 47 | F228: 0.09 | G228: MAYO
A229: 35613 | B229: 69768.04 | C229: =B229+(B229*F229/365*E229)*1 -> 70657.821 | D229: =A229+E229 -> 35662 | E229: 49 | F229: 0.095 | G229: MAYO
A230: 35614 | B230: 5000 | C230: =B230+(B230*F230/365*E230)*1 -> 5059.1781 | D230: =A230+E230 -> 35662 | E230: 48 | F230: 0.09 | G230: MAYO
A231: 35615 | B231: 3000 | C231: =B231+(B231*F231/365*E231)*1 -> 3034.7671 | D231: =A231+E231 -> 35662 | E231: 47 | F231: 0.09 | G231: MAYO
...

Sheet POR BANC
A3: Etiquetas de fila | B3: Suma de ACOBRAR
A4: BBVA BANCO | B4: 6678632.6
A5: BBVA BANCO BARBARA | B5: 4252055.6
A6: BBVA BANCO RAMONA | B6: 4103689.9
A7: BNA BANCO | B7: 4815311
A8: BNA JUBIL. BANCO | B8: 5248067.3
A9: BNA RAMONA | B9: 2615432.3
A10: HSBC BANCO | B10: 31867807
A11: HSBC BANCO MARIA | B11: 7885593
A12: ITAU BANCO | B12: 24822088
A13: Total general | B13: 92288676

Sheet  PF ANTERIORES U$S
A1: Fecha | B1: Depositado | C1: A Cobrar | D1: Dias | E1: Fecha Vto. | F1: Tasa
A3: 39701 | B3: 62768 | C3: =B3+(B3*F3/365*D3)*1 -> 62957.594 | D3: 35 | E3: =A3+D3 -> 39736 | F3: 0.0315 | G3: HSBC | H3: =+A657 -> 37239 | I3: =+B657 -> 15000 | J3: =+C658 -> 714.28571 | K3: =+E657 -> 13865.714 | L3: =+D657 -> 420 | M3: =+G657 -> 0 | N3: =+F657 -> 0 | O3: =+J3-I3 -> -14285.714
A4: 39800 | B4: 180000 | C4: =B4+(B4*F4/365*D4)*1 -> 180536.55 | D4: 34 | E4: =A4+D4 -> 39834 | F4: 0.032 | G4: HSBC | H4: =+A658 -> 37242 | I4: =+B658 -> 20000 | J4: =+C659 -> 952.38095 | K4: =+E658 -> 18627.619 | L4: =+D658 -> 420 | M4: =+G658 -> 0 | N4: =+F658 -> 0 | O4: =+J4-I4 -> -19047.619
A5: 39800 | B5: 80000 | C5: =B5+(B5*F5/365*D5)*1 -> 80238.466 | D5: 34 | E5: =A5+D5 -> 39834 | F5: 0.032 | G5: HSBC | H5: =+A658 -> 37242 | I5: =+B658 -> 20000 | J5: =+C659 -> 952.38095 | K5: =+E658 -> 18627.619 | L5: =+D658 -> 420 | M5: =+G658 -> 0 | N5: =+F658 -> 0 | O5: =+J5-I5 -> -19047.619
A6: 39834 | B6: 180537 | C6: =B6+(B6*F6/365*D6)*1 -> 181056.35 | D6: 35 | E6: =A6+D6 -> 39869 | F6: 0.03 | G6: HSBC | H6: =+A659 -> 37252 | I6: =+B659 -> 20000 | J6: =+C660 -> 952.38095 | K6: =+E659 -> 19047.619 | L6: =+D659 -> 0 | M6: =+G659 -> 0 | N6: =+F659 -> 0 | O6: =+J6-I6 -> -19047.619
A7: 39834 | B7: 80238 | C7: =B7+(B7*F7/365*D7)*1 -> 80468.822 | D7: 35 | E7: =A7+D7 -> 39869 | F7: 0.03 | G7: HSBC | H7: =+A659 -> 37252 | I7: =+B659 -> 20000 | J7: =+C660 -> 952.38095 | K7: =+E659 -> 19047.619 | L7: =+D659 -> 0 | M7: =+G659 -> 0 | N7: =+F659 -> 0 | O7: =+J7-I7 -> -19047.619
A8: 39864 | B8: 135000 | C8: =B8+(B8*F8/365*D8)*1 -> 135274.62 | D8: 33 | E8: =A8+D8 -> 39897 | F8: 0.0225 | G8: HSBC | H8: =+#REF! -> #REF! | I8: =+#REF! -> #REF! | J8: =+#REF! -> #REF! | K8: =+#REF! -> #REF! | L8: =+#REF! -> #REF! | M8: =+#REF! -> #REF! | N8: =+#REF! -> #REF! | O8: =+J8-I8 -> #REF!
A9: 39869 | B9: 181056 | C9: =B9+(B9*F9/365*D9)*1 -> 181472.68 | D9: 35 | E9: =A9+D9 -> 39904 | F9: 0.024 | G9: HSBC | H9: =+#REF! -> #REF! | I9: =+#REF! -> #REF! | J9: =+#REF! -> #REF! | K9: =+#REF! -> #REF! | L9: =+#REF! -> #REF! | M9: =+#REF! -> #REF! | N9: =+#REF! -> #REF! | O9: =+J9-I9 -> #REF!
A10: 39869 | B10: 80469 | C10: =B10+(B10*F10/365*D10)*1 -> 80654.189 | D10: 35 | E10: =A10+D10 -> 39904 | F10: 0.024 | G10: HSBC | H10: =+A659 -> 37252 | I10: =+B659 -> 20000 | J10: =+C660 -> 952.38095 | K10: =+E659 -> 19047.619 | L10: =+D659 -> 0 | M10: =+G659 -> 0 | N10: =+F659 -> 0 | O10: =+J10-I10 -> -19047.619
A11: 39871 | B11: 89300 | C11: =B11+(B11*F11/365*D11)*1 -> 89380.737 | D11: 33 | E11: =A11+D11 -> 39904 | F11: 0.01 | G11: BBVA | H11: =+A659 -> 37252 | I11: =+B659 -> 20000 | J11: =+C660 -> 952.38095 | K11: =+E659 -> 19047.619 | L11: =+D659 -> 0 | M11: =+G659 -> 0 | N11: =+F659 -> 0 | O11: =+J11-I11 -> -19047.619
A12: 39876 | B12: 45000 | C12: =B12+(B12*F12/365*D12)*1 -> 45043.151 | D12: 35 | E12: =A12+D12 -> 39911 | F12: 0.01 | G12: BBVA | H12: =+A659 -> 37252 | I12: =+B659 -> 20000 | J12: =+C660 -> 952.38095 | K12: =+E659 -> 19047.619 | L12: =+D659 -> 0 | M12: =+G659 -> 0 | N12: =+F659 -> 0 | O12: =+J12-I12 -> -19047.619
A13: 39897 | B13: 135275 | C13: =B13+(B13*F13/365*D13)*1 -> 135508.49 | D13: 30 | E13: =A13+D13 -> 39927 | F13: 0.021 | G13: HSBC | H13: =+#REF! -> #REF! | I13: =+#REF! -> #REF! | J13: =+#REF! -> #REF! | K13: =+#REF! -> #REF! | L13: =+#REF! -> #REF! | M13: =+#REF! -> #REF! | N13: =+#REF! -> #REF! | O13: =+J13-I13 -> #REF!
A14: 39904 | B14: 181473 | C14: =B14+(B14*F14/365*D14)*1 -> 181838.43 | D14: 35 | E14: =A14+D14 -> 39939 | F14: 0.021 | G14: HSBC | H14: =+#REF! -> #REF! | I14: =+#REF! -> #REF! | J14: =+#REF! -> #REF! | K14: =+#REF! -> #REF! | L14: =+#REF! -> #REF! | M14: =+#REF! -> #REF! | N14: =+#REF! -> #REF! | O14: =+J14-I14 -> #REF!
A15: 39904 | B15: 80654 | C15: =B15+(B15*F15/365*D15)*1 -> 80816.413 | D15: 35 | E15: =A15+D15 -> 39939 | F15: 0.021 | G15: HSBC | H15: =+A659 -> 37252 | I15: =+B659 -> 20000 | J15: =+C660 -> 952.38095 | K15: =+E659 -> 19047.619 | L15: =+D659 -> 0 | M15: =+G659 -> 0 | N15: =+F659 -> 0 | O15: =+J15-I15 -> -19047.619
A16: 39904 | B16: 89381 | C16: =B16+(B16*F16/365*D16)*1 -> 89560.986 | D16: 35 | E16: =A16+D16 -> 39939 | F16: 0.021 | G16: HSBC | H16: =+A660 -> 37253 | I16: =+B660 -> 20000 | J16: =+C661 -> 952.38095 | K16: =+E660 -> 19047.619 | L16: =+D660 -> 0 | M16: =+G660 -> 0 | N16: =+F660 -> 0 | O16: =+J16-I16 -> -19047.619
A17: 39911 | B17: 45950 | C17: =B17+(B17*F17/365*D17)*1 -> 46038.123 | D17: 35 | E17: =A17+D17 -> 39946 | F17: 0.02 | G17: HSBC | H17: =+CARTERA!#REF! -> #REF! | I17: =+CARTERA!#REF! -> #REF! | J17: =+CARTERA!#REF! -> #REF! | K17: =+CARTERA!#REF! -> #REF! | L17: =+CARTERA!#REF! -> #REF! | M17: =+CARTERA!#REF! -> #REF! | N17: =+CARTERA!#REF! -> #REF! | O17: =+J17-I17 -> #REF!
A18: 39947 | B18: 46038 | C18: =B18+(B18*F18/365*D18)*1 -> 46093.75 | D18: 34 | E18: =A18+D18 -> 39981 | F18: 0.013 | G18: HSBC | H18: =+A660 -> 37253 | I18: =+B660 -> 20000 | J18: =+C661 -> 952.38095 | K18: =+E660 -> 19047.619 | L18: =+D660 -> 0 | M18: =+G660 -> 0 | N18: =+F660 -> 0 | O18: =+J18-I18 -> -19047.619
A19: 39927 | B19: 135508 | C19: =B19+(B19*F19/365*D19)*1 -> 135908.96 | D19: 60 | E19: =A19+D19 -> 39987 | F19: 0.018 | G19: HSBC | H19: =+#REF! -> #REF! | I19: =+#REF! -> #REF! | J19: =+#REF! -> #REF! | K19: =+#REF! -> #REF! | L19: =+#REF! -> #REF! | M19: =+#REF! -> #REF! | N19: =+#REF! -> #REF! | O19: =+J19-I19 -> #REF!
A20: 39940 | B20: 181838 | C20: =B20+(B20*F20/365*D20)*1 -> 182363.09 | D20: 62 | E20: =A20+D20 -> 40002 | F20: 0.017 | G20: HSBC | H20: =+#REF! -> #REF! | I20: =+#REF! -> #REF! | J20: =+#REF! -> #REF! | K20: =+#REF! -> #REF! | L20: =+#REF! -> #REF! | M20: =+#REF! -> #REF! | N20: =+#REF! -> #REF! | O20: =+J20-I20 -> #REF!
A21: 39940 | B21: 80816 | C21: =B21+(B21*F21/365*D21)*1 -> 81049.37 | D21: 62 | E21: =A21+D21 -> 40002 | F21: 0.017 | G21: HSBC | H21: =+A659 -> 37252 | I21: =+B659 -> 20000 | J21: =+C660 -> 952.38095 | K21: =+E659 -> 19047.619 | L21: =+D659 -> 0 | M21: =+G659 -> 0 | N21: =+F659 -> 0 | O21: =+J21-I21 -> -19047.619
A22: 39940 | B22: 89561 | C22: =B22+(B22*F22/365*D22)*1 -> 89819.623 | D22: 62 | E22: =A22+D22 -> 40002 | F22: 0.017 | G22: HSBC | H22: =+A660 -> 37253 | I22: =+B660 -> 20000 | J22: =+C661 -> 952.38095 | K22: =+E660 -> 19047.619 | L22: =+D660 -> 0 | M22: =+G660 -> 0 | N22: =+F660 -> 0 | O22: =+J22-I22 -> -19047.619
A23: 39940 | B23: 27571 | C23: =B23+(B23*F23/365*D23)*1 -> 27650.616 | D23: 62 | E23: =A23+D23 -> 40002 | F23: 0.017 | G23: HSBC | H23: =+A660 -> 37253 | I23: =+B660 -> 20000 | J23: =+C661 -> 952.38095 | K23: =+E660 -> 19047.619 | L23: =+D660 -> 0 | M23: =+G660 -> 0 | N23: =+F660 -> 0 | O23: =+J23-I23 -> -19047.619
A24: 40002 | B24: 81049 | C24: =B24+(B24*F24/365*D24)*1 -> 81128.939 | D24: 30 | E24: =A24+D24 -> 40032 | F24: 0.012 | G24: HSBC | H24: =+#REF! -> #REF! | I24: =+#REF! -> #REF! | J24: =+#REF! -> #REF! | K24: =+#REF! -> #REF! | L24: =+#REF! -> #REF! | M24: =+#REF! -> #REF! | N24: =+#REF! -> #REF! | O24: =+J24-I24 -> #REF!
A25: 40002 | B25: 89820 | C25: =B25+(B25*F25/365*D25)*1 -> 89908.59 | D25: 30 | E25: =A25+D25 -> 40032 | F25: 0.012 | G25: HSBC
A26: 40002 | B26: 182363 | C26: =B26+(B26*F26/365*D26)*1 -> 182789.68 | D26: 61 | E26: =A26+D26 -> 40063 | F26: 0.014 | G26: HSBC
A27: 40002 | B27: 27651 | C27: =B27+(B27*F27/365*D27)*1 -> 27715.696 | D27: 61 | E27: =A27+D27 -> 40063 | F27: 0.014 | G27: HSBC
A28: 39994 | B28: 135909 | C28: =B28+(B28*F28/365*D28)*1 -> 136422.85 | D28: 92 | E28: =A28+D28 -> 40086 | F28: 0.015 | G28: HSBC
A29: 40030 | B29: 47571 | C29: =B29+(B29*F29/365*D29)*1 -> 47694.228 | D29: 61 | E29: =A29+D29 -> 40091 | F29: 0.0155 | G29: HSBC
A30: 40030 | B30: 12493 | C30: =B30+(B30*F30/365*D30)*1 -> 12525.362 | D30: 61 | E30: =A30+D30 -> 40091 | F30: 0.0155 | G30: HSBC
A31: 40032 | B31: 81129 | C31: =B31+(B31*F31/365*D31)*1 -> 81298.482 | D31: 61 | E31: =A31+D31 -> 40093 | F31: 0.0125 | G31: HSBC
A32: 40032 | B32: 89909 | C32: =B32+(B32*F32/365*D32)*1 -> 90096.824 | D32: 61 | E32: =A32+D32 -> 40093 | F32: 0.0125 | G32: HSBC
A33: 40087 | B33: 136423 | C33: =B33+(B33*F33/365*D33)*1 -> 136527.65 | D33: 35 | E33: =A33+D33 -> 40122 | F33: 0.008 | G33: HSBC
A34: 40063 | B34: 182790 | C34: =B34+(B34*F34/365*D34)*1 -> 183442.03 | D34: 93 | E34: =A34+D34 -> 40156 | F34: 0.014 | G34: HSBC
A35: 40063 | B35: 27716 | C35: =B35+(B35*F35/365*D35)*1 -> 27814.866 | D35: 93 | E35: =A35+D35 -> 40156 | F35: 0.014 | G35: HSBC
A36: 40122 | B36: 136528 | C36: =B36+(B36*F36/365*D36)*1 -> 136604.31 | D36: 34 | E36: =A36+D36 -> 40156 | F36: 0.006 | G36: HSBC | H36: =+C37-B37 -> 7726.9176
B37: =SUM(B4:B36) -> 3377016 | C37: =SUM(C4:C36) -> 3384742.9
A38: 40093 | B38: 47694 | C38: =B38+(B38*F38/365*D38)*1 -> 47836.69 | D38: 91 | E38: =A38+D38 -> 40184 | F38: 0.012 | G38: HSBC
A39: 40093 | B39: 12525 | C39: =B39+(B39*F39/365*D39)*1 -> 12562.472 | D39: 91 | E39: =A39+D39 -> 40184 | F39: =+F38 -> 0.012 | G39: HSBC
A40: 40156 | B40: 27815 | C40: =B40+(B40*F40/365*D40)*1 -> 27848.607 | D40: 63 | E40: =A40+D40 -> 40219 | F40: 0.007 | G40: HSBC
A41: 40156 | B41: 136604 | C41: =B41+(B41*F41/365*D41)*1 -> 136769.05 | D41: 63 | E41: =A41+D41 -> 40219 | F41: 0.007 | G41: HSBC
A42: 40093 | B42: 81298 | C42: =B42+(B42*F42/365*D42)*1 -> 81718.968 | D42: 126 | E42: =A42+D42 -> 40219 | F42: 0.015 | G42: HSBC
A43: 40156 | B43: 183442 | C43: =B43+(B43*F43/365*D43)*1 -> 183807.88 | D43: 91 | E43: =A43+D43 -> 40247 | F43: 0.008 | G43: HSBC | H43: =SUM(C38:C44) -> 581286.89
A44: 40093 | B44: 90097 | C44: =B44+(B44*F44/365*D44)*1 -> 90743.23 | D44: 154 | E44: =A44+D44 -> 40247 | F44: 0.017 | G44: HSBC
A45: 40219 | B45: 47837 | C45: =B45+(B45*F45/365*D45)*1 -> 47859.936 | D45: 35 | E45: =A45+D45 -> 40254 | F45: 0.005 | G45: HSBC
A46: 40219 | B46: 12562 | C46: =B46+(B46*F46/365*D46)*1 -> 12568.023 | D46: 35 | E46: =A46+D46 -> 40254 | F46: 0.005 | G46: HSBC
A47: 40219 | B47: 27849 | C47: =B47+(B47*F47/365*D47)*1 -> 27862.352 | D47: 35 | E47: =A47+D47 -> 40254 | F47: 0.005 | G47: HSBC
A48: 40219 | B48: 136769 | C48: =B48+(B48*F48/365*D48)*1 -> 136834.57 | D48: 35 | E48: =A48+D48 -> 40254 | F48: 0.005 | G48: HSBC
A49: 40219 | B49: 81719 | C49: =B49+(B49*F49/365*D49)*1 -> 81758.18 | D49: 35 | E49: =A49+D49 -> 40254 | F49: 0.005 | G49: HSBC
A50: 40247 | B50: 183807.88 | C50: =B50+(B50*F50/365*D50)*1 -> 183896.01 | D50: 35 | E50: =A50+D50 -> 40282 | F50: 0.005 | G50: HSBC
A51: 40247 | B51: 90743.23 | C51: =B51+(B51*F51/365*D51)*1 -> 90786.737 | D51: 35 | E51: =A51+D51 -> 40282 | F51: 0.005 | G51: HSBC
A52: 40256 | B52: 47860 | C52: =B52+(B52*F52/365*D52)*1 -> 47881.635 | D52: 33 | E52: =A52+D52 -> 40289 | F52: 0.005 | G52: HSBC
A53: 40256 | B53: 12568 | C53: =B53+(B53*F53/365*D53)*1 -> 12573.681 | D53: 33 | E53: =A53+D53 -> 40289 | F53: 0.005 | G53: HSBC
A54: 40256 | B54: 27862 | C54: =B54+(B54*F54/365*D54)*1 -> 27874.595 | D54: 33 | E54: =A54+D54 -> 40289 | F54: 0.005 | G54: HSBC
A55: 40256 | B55: 136835 | C55: =B55+(B55*F55/365*D55)*1 -> 136896.86 | D55: 33 | E55: =A55+D55 -> 40289 | F55: 0.005 | G55: HSBC
... A57: 40274 | B57: 20000 | C57: =B57+(B57*F57/365*D57)*1 -> 20007.89 | D57: 36 | E57: =A57+D57 -> 40310 | F57: 0.004 | G57: HSBC
A58: 40283 | B58: 183896 | C58: =B58+(B58*F58/365*D58)*1 -> 183973.09 | D58: 34 | E58: =A58+D58 -> 40317 | F58: 0.0045 | G58: HSBC | H58: =SUM(C52:C59) -> 601827.76
A59: 40283 | B59: 90787 | C59: =B59+(B59*F59/365*D59)*1 -> 90825.056 | D59: 34 | E59: =A59+D59 -> 40317 | F59: 0.0045 | G59: HSBC
A60: 40289 | B60: 47882 | C60: =B60+(B60*F60/365*D60)*1 -> 47904.957 | D60: 35 | E60: =A60+D60 -> 40324 | F60: 0.005 | G60: HSBC
A61: 40289 | B61: 12574 | C61: =B61+(B61*F61/365*D61)*1 -> 12580.029 | D61: 35 | E61: =A61+D61 -> 40324 | F61: 0.005 | G61: HSBC
A62: 40289 | B62: 27875 | C62: =B62+(B62*F62/365*D62)*1 -> 27888.365 | D62: 35 | E62: =A62+D62 -> 40324 | F62: 0.005 | G62: HSBC
A63: 40289 | B63: 81795 | C63: =B63+(B63*F63/365*D63)*1 -> 81842.06 | D63: 42 | E63: =A63+D63 -> 40331 | F63: 0.005 | G63: HSBC
A64: 40289 | B64: 136897 | C64: =B64+(B64*F64/365*D64)*1 -> 136988.89 | D64: 49 | E64: =A64+D64 -> 40338 | F64: 0.005 | G64: HSBC
A65: 40310 | B65: 20008 | C65: =B65+(B65*F65/365*D65)*1 -> 20015.674 | D65: 35 | E65: =A65+D65 -> 40345 | F65: 0.004 | G65: HSBC
A66: 40317 | B66: 183973 | C66: =B66+(B66*F66/365*D66)*1 -> 184052.39 | D66: 35 | E66: =A66+D66 -> 40352 | F66: 0.0045 | G66: HSBC | H66: =SUM(C60:C67) -> 602136.55
A67: 40317 | B67: 90825 | C67: =B67+(B67*F67/365*D67)*1 -> 90864.192 | D67: 35 | E67: =A67+D67 -> 40352 | F67: 0.0045 | G67: HSBC
A68: 40326 | B68: 47905 | C68: =B68+(B68*F68/365*D68)*1 -> 47928.821 | D68: 33 | E68: =A68+D68 -> 40359 | F68: 0.0055 | G68: HSBC
A69: 40326 | B69: 12580 | C69: =B69+(B69*F69/365*D69)*1 -> 12586.256 | D69: 33 | E69: =A69+D69 -> 40359 | F69: 0.0055 | G69: HSBC
A70: 40326 | B70: 27888 | C70: =B70+(B70*F70/365*D70)*1 -> 27901.868 | D70: 33 | E70: =A70+D70 -> 40359 | F70: 0.0055 | G70: HSBC
A71: 40331 | B71: 81842 | C71: =B71+(B71*F71/365*D71)*1 -> 81881.239 | D71: 35 | E71: =A71+D71 -> 40366 | F71: 0.005 | G71: HSBC
A72: 40331 | B72: 14400 | C72: =B72+(B72*F72/365*D72)*1 -> 14406.904 | D72: 35 | E72: =A72+D72 -> 40366 | F72: 0.005 | G72: HSBC
A73: 40333 | B73: 24134 | C73: =B73+(B73*F73/365*D73)*1 -> 24146.001 | D73: 33 | E73: =A73+D73 -> 40366 | F73: 0.0055 | G73: HSBC
A74: 40338 | B74: 136989 | C74: =B74+(B74*F74/365*D74)*1 -> 137061.25 | D74: 35 | E74: =A74+D74 -> 40373 | F74: 0.0055 | G74: HSBC
A75: 40338 | B75: 13000 | C75: =B75+(B75*F75/365*D75)*1 -> 13006.856 | D75: 35 | E75: =A75+D75 -> 40373 | F75: 0.0055 | G75: HSBC
A76: 40347 | B76: 20016 | C76: =B76+(B76*F76/365*D76)*1 -> 20025.953 | D76: 33 | E76: =A76+D76 -> 40380 | F76: 0.0055 | G76: HSBC
A77: 40347 | B77: =60489.4/3.95 -> 15313.772 | C77: =B77+(B77*F77/365*D77)*1 -> 15351.532 | D77: 90 | E77: =A77+D77 -> 40437 | F77: 0.01 | G77: BANCO HIPOTECARIO
A78: 40352 | B78: 184052 | C78: =B78+(B78*F78/365*D78)*1 -> 184140.24 | D78: 35 | E78: =A78+D78 -> 40387 | F78: 0.005 | G78: HSBC | H78: =SUM(C68:C79) -> 669344.49
A79: 40352 | B79: 90864 | C79: =B79+(B79*F79/365*D79)*1 -> 90907.565 | D79: 35 | E79: =A79+D79 -> 40387 | F79: 0.005 | G79: HSBC
A80: 40359 | B80: 47929 | C80: =B80+(B80*F80/365*D80)*1 -> 47951.98 | D80: 35 | E80: =A80+D80 -> 40394 | F80: 0.005 | G80: HSBC
A81: 40359 | B81: 12586 | C81: =B81+(B81*F81/365*D81)*1 -> 12592.034 | D81: 35 | E81: =A81+D81 -> 40394 | F81: 0.005 | G81: HSBC
A82: 40359 | B82: 27902 | C82: =B82+(B82*F82/365*D82)*1 -> 27915.378 | D82: 35 | E82: =A82+D82 -> 40394 | F82: 0.005 | G82: HSBC
A83: 40366 | B83: 81881 | C83: =B83+(B83*F83/365*D83)*1 -> 81912.406 | D83: 35 | E83: =A83+D83 -> 40401 | F83: 0.004 | G83: HSBC
A84: 40366 | B84: 14407 | C84: =B84+(B84*F84/365*D84)*1 -> 14412.526 | D84: 35 | E84: =A84+D84 -> 40401 | F84: 0.004 | G84: HSBC
A85: 40366 | B85: 24146 | C85: =B85+(B85*F85/365*D85)*1 -> 24155.261 | D85: 35 | E85: =A85+D85 -> 40401 | F85: 0.004 | G85: HSBC
A86: 40374 | B86: 13007 | C86: =B86+(B86*F86/365*D86)*1 -> 13011.846 | D86: 34 | E86: =A86+D86 -> 40408 | F86: 0.004 | G86: HSBC
A87: 40374 | B87: 137061 | C87: =B87+(B87*F87/365*D87)*1 -> 137112.07 | D87: 34 | E87: =A87+D87 -> 40408 | F87: 0.004 | G87: HSBC
A88: 40386 | B88: 20026 | C88: =B88+(B88*F88/365*D88)*1 -> 20061.718 | D88: 93 | E88: =A88+D88 -> 40479 | F88: 0.007 | G88: HSBC
A89: 40386 | B89: 14447 | C89: =B89+(B89*F89/365*D89)*1 -> 14472.767 | D89: 93 | E89: =A89+D89 -> 40479 | F89: 0.007 | G89: HSBC
A90: 40387 | B90: 90908 | C90: =B90+(B90*F90/365*D90)*1 -> 90951.586 | D90: 35 | E90: =A90+D90 -> 40422 | F90: 0.005 | G90: HSBC | H90: =SUM(C80:C91) -> 668880.27
A91: 40387 | B91: 184140 | C91: =B91+(B91*F91/365*D91)*1 -> 184330.7 | D91: 63 | E91: =A91+D91 -> 40450 | F91: 0.006 | G91: HSBC
A92: 40394 | B92: 47952 | C92: =B92+(B92*F92/365*D92)*1 -> 47974.991 | D92: 35 | E92: =A92+D92 -> 40429 | F92: 0.005 | G92: HSBC
A93: 40394 | B93: 12592 | C93: =B93+(B93*F93/365*D93)*1 -> 12598.037 | D93: 35 | E93: =A93+D93 -> 40429 | F93: 0.005 | G93: HSBC
A94: 40394 | B94: 27915 | C94: =B94+(B94*F94/365*D94)*1 -> 27928.384 | D94: 35 | E94: =A94+D94 -> 40429 | F94: 0.005 | G94: HSBC
A95: 40394 | B95: 46282 | C95: =B95+(B95*F95/365*D95)*1 -> 46329.93 | D95: 63 | E95: =A95+D95 -> 40457 | F95: 0.006 | G95: HSBC
A96: 40394 | B96: 12155 | C96: =B96+(B96*F96/365*D96)*1 -> 12167.588 | D96: 63 | E96: =A96+D96 -> 40457 | F96: 0.006 | G96: HSBC
A97: 40403 | B97: 81912 | C97: =B97+(B97*F97/365*D97)*1 -> 81941.623 | D97: 33 | E97: =A97+D97 -> 40436 | F97: 0.004 | G97: HSBC
A98: 40403 | B98: 14413 | C98: =B98+(B98*F98/365*D98)*1 -> 14418.212 | D98: 33 | E98: =A98+D98 -> 40436 | F98: 0.004 | G98: HSBC
A99: 40403 | B99: 24155 | C99: =B99+(B99*F99/365*D99)*1 -> 24163.736 | D99: 33 | E99: =A99+D99 -> 40436 | F99: 0.004 | G99: HSBC
A100: 40408 | B100: 13012 | C100: =B100+(B100*F100/365*D100)*1 -> 13016.367 | D100: 35 | E100: =A100+D100 -> 40443 | F100: 0.0035 | G100: HSBC
A101: 40408 | B101: 137112 | C101: =B101+(B101*F101/365*D101)*1 -> 137218.5 | D101: 63 | E101: =A101+D101 -> 40471 | F101: 0.0045 | G101: HSBC
A102: 40422 | B102: 90952 | C102: =B102+(B102*F102/365*D102)*1 -> 90986.886 | D102: 35 | E102: =A102+D102 -> 40457 | F102: 0.004 | G102: HSBC
...

Sheet Hoja1
A1: Fecha | B1: Depositado | C1: A Cobrar | D1: Fecha Vto. | E1: Dias | F1: Tasa | G1: titular
A2: 44531 | B2: 90000 | C2: =B2+(B2*F2/365*E2)*1 -> 93010.685 | D2: =+A2+E2 -> 44564 | E2: 33 | F2: 0.37 | G2: HSBC MARIA
A3: 44533 | B3: 28000 | C3: =B3+(B3*F3/365*E3)*1 -> 28879.89 | D3: =+A3+E3 -> 44564 | E3: 31 | F3: 0.37 | G3: CIUDAD
A4: 44533 | B4: 110000 | C4: =B4+(B4*F4/365*E4)*1 -> 113456.71 | D4: =+A4+E4 -> 44564 | E4: 31 | F4: 0.37 | G4: BBVA
A5: 44536 | B5: 31000 | C5: =B5+(B5*F5/365*E5)*1 -> 31942.74 | D5: =+A5+E5 -> 44566 | E5: 30 | F5: 0.37 | G5: CIUDAD
A6: 44536 | B6: 27000 | C6: =B6+(B6*F6/365*E6)*1 -> 27821.096 | D6: =+A6+E6 -> 44566 | E6: 30 | F6: 0.37 | G6: BBVA
A7: 44540 | B7: 8900 | C7: =B7+(B7*F7/365*E7)*1 -> 9179.6795 | D7: =+A7+E7 -> 44571 | E7: 31 | F7: 0.37 | G7: CIUDAD
A8: 44540 | B8: 27000 | C8: =B8+(B8*F8/365*E8)*1 -> 27848.466 | D8: =+A8+E8 -> 44571 | E8: 31 | F8: 0.37 | G8: BBVA
A9: 44543 | B9: 160000 | C9: =B9+(B9*F9/365*E9)*1 -> 164865.75 | D9: =+A9+E9 -> 44573 | E9: 30 | F9: 0.37 | G9: BBVA
A10: 44543 | B10: 51600 | C10: =B10+(B10*F10/365*E10)*1 -> 53169.205 | D10: =+A10+E10 -> 44573 | E10: 30 | F10: 0.37 | G10: CIUDAD
A11: 44545 | B11: 47300 | C11: =B11+(B11*F11/365*E11)*1 -> 48738.438 | D11: =+A11+E11 -> 44575 | E11: 30 | F11: 0.37 | G11: BNA
A12: 44545 | B12: 14000 | C12: =B12+(B12*F12/365*E12)*1 -> 14425.753 | D12: =+A12+E12 -> 44575 | E12: 30 | F12: 0.37 | G12: BBVA
A13: 44546 | B13: 100000 | C13: =B13+(B13*F13/365*E13)*1 -> 103243.84 | D13: =+A13+E13 -> 44578 | E13: 32 | F13: 0.37 | G13: HSBC
... A42: 44564 | B42: 29400 | C42: =B42+(B42*F42/365*E42)*1 -> 30294.082 | D42: =+A42+E42 -> 44594 | E42: 30 | F42: 0.37 | G42: CIUDAD
A43: 44564 | B43: 150000 | C43: =B43+(B43*F43/365*E43)*1 -> 154561.64 | D43: =+A43+E43 -> 44594 | E43: 30 | F43: 0.37 | G43: HSBC MARIA | H43: =SUM(C43:C43) -> 154561.64
A44: 44564 | B44: 18500 | C44: =B44+(B44*F44/365*E44)*1 -> 19062.603 | D44: =+A44+E44 -> 44594 | E44: 30 | F44: 0.37 | G44: BNA | U44: 49314
A45: 44566 | B45: 26900 | C45: =B45+(B45*F45/365*E45)*1 -> 27718.055 | D45: =+A45+E45 -> 44596 | E45: 30 | F45: 0.37 | G45: CIUDAD
A46: 44566 | B46: 25000 | C46: =B46+(B46*F46/365*E46)*1 -> 25760.274 | D46: =+A46+E46 -> 44596 | E46: 30 | F46: 0.37 | G46: BBVA RAMONA
A47: 44573 | B47: 160000 | C47: =B47+(B47*F47/365*E47)*1 -> 165128.77 | D47: =+A47+E47 -> 44603 | E47: 30 | F47: 0.39 | G47: BBVA
A48: 44573 | B48: 53200 | C48: =B48+(B48*F48/365*E48)*1 -> 54905.315 | D48: =+A48+E48 -> 44603 | E48: 30 | F48: 0.39 | G48: CIUDAD
A49: 44574 | B49: 18000 | C49: =B49+(B49*F49/365*E49)*1 -> 18615.452 | D49: =+A49+E49 -> 44606 | E49: 32 | F49: 0.39 | G49: BBVA | U49: 49314
A50: 44574 | B50: 56000 | C50: =B50+(B50*F50/365*E50)*1 -> 57914.74 | D50: =+A50+E50 -> 44606 | E50: 32 | F50: 0.39 | G50: BBVA RAMONA
A51: 44575 | B51: 5000 | C51: =B51+(B51*F51/365*E51)*1 -> 5165.6164 | D51: =+A51+E51 -> 44606 | E51: 31 | F51: 0.39 | G51: HSBC
A52: 44578 | B52: 79700 | C52: =B52+(B52*F52/365*E52)*1 -> 82254.767 | D52: =+A52+E52 -> 44608 | E52: 30 | F52: 0.39 | G52: BBVA BARBARA
A53: 44578 | B53: 124200 | C53: =B53+(B53*F53/365*E53)*1 -> 128181.21 | D53: =+A53+E53 -> 44608 | E53: 30 | F53: 0.39 | G53: BBVA RAMONA | U53: 49314
A54: 44578 | B54: 19100 | C54: =B54+(B54*F54/365*E54)*1 -> 19712.247 | D54: =+A54+E54 -> 44608 | E54: 30 | F54: 0.39 | G54: CIUDAD
A55: 44580 | B55: 61000 | C55: =B55+(B55*F55/365*E55)*1 -> 62955.342 | D55: =+A55+E55 -> 44610 | E55: 30 | F55: 0.39 | G55: BBVA RAMONA | H55: =SUM(C55:C55) -> 62955.342
A56: 44575 | B56: 65000 | C56: =B56+(B56*F56/365*E56)*1 -> 73841.86 | D56: =+A56+E56 -> 44669 | E56: 94 | F56: 0.52819622 | G56: BBVA UVA
A57: 44575 | B57: 48800 | C57: =B57+(B57*F57/365*E57)*1 -> 55167.92 | D57: =+A57+E57 -> 44669 | E57: 94 | F57: 0.50669053 | G57: BNA UVA
A58: 44581 | B58: 120000 | C58: =B58+(B58*F58/365*E58)*1 -> 124103.01 | D58: =+A58+E58 -> 44613 | E58: 32 | F58: 0.39 | G58: HSBC MARIA | H58: =SUM(C58:C58) -> 124103.01
A59: 44581 | B59: 55000 | C59: =B59+(B59*F59/365*E59)*1 -> 56880.548 | D59: =+A59+E59 -> 44613 | E59: 32 | F59: 0.39 | G59: HSBC MARIA
A60: 44585 | B60: 9300 | C60: =B60+(B60*F60/365*E60)*1 -> 9598.1096 | D60: =+A60+E60 -> 44615 | E60: 30 | F60: 0.39 | G60: CIUDAD
A61: 44585 | B61: 54000 | C61: =B61+(B61*F61/365*E61)*1 -> 55730.959 | D61: =+A61+E61 -> 44615 | E61: 30 | F61: 0.39 | G61: BBVA RAMONA
A62: 44585 | B62: 20000 | C62: =B62+(B62*F62/365*E62)*1 -> 20641.096 | D62: =+A62+E62 -> 44615 | E62: 30 | F62: 0.39 | G62: BBVA BARBARA | H62: =SUM(C62:C62) -> 20641.096
A63: 44580 | B63: 159000 | C63: =B63+(B63*F63/365*E63)*1 -> 164096.71 | D63: =+A63+E63 -> 44610 | E63: 30 | F63: 0.39 | G63: BNA | H63: =SUM(C63:C63) -> 164096.71
A64: 44580 | B64: 51000 | C64: =B64+(B64*F64/365*E64)*1 -> 52634.795 | D64: =+A64+E64 -> 44610 | E64: 30 | F64: 0.39 | G64: BBVA
A65: 44587 | B65: 295500 | C65: =B65+(B65*F65/365*E65)*1 -> 304972.19 | D65: =+A65+E65 -> 44617 | E65: 30 | F65: 0.39 | G65: BBVA RAMONA
A66: 44587 | B66: 6600 | C66: =B66+(B66*F66/365*E66)*1 -> 6811.5616 | D66: =+A66+E66 -> 44617 | E66: 30 | F66: 0.39 | G66: BBVA BARBARA
A67: 44585 | B67: 20000 | C67: =B67+(B67*F67/365*E67)*1 -> 20641.096 | D67: =+A67+E67 -> 44615 | E67: 30 | F67: 0.39 | G67: BBVA
A68: 44587 | B68: 52600 | C68: =B68+(B68*F68/365*E68)*1 -> 54286.082 | D68: =+A68+E68 -> 44617 | E68: 30 | F68: 0.39 | G68: CIUDAD
A69: 44585 | B69: 8800 | C69: =B69+(B69*F69/365*E69)*1 -> 9082.0822 | D69: =+A69+E69 -> 44615 | E69: 30 | F69: 0.39 | G69: BNA
A70: 44587 | B70: 70000 | C70: =B70+(B70*F70/365*E70)*1 -> 72243.836 | D70: =+A70+E70 -> 44617 | E70: 30 | F70: 0.39 | G70: HSBC MARIA
A71: 44587 | B71: 150000 | C71: =B71+(B71*F71/365*E71)*1 -> 154808.22 | D71: =+A71+E71 -> 44617 | E71: 30 | F71: 0.39 | G71: HSBC
A72: 44589 | B72: 17400 | C72: =B72+(B72*F72/365*E72)*1 -> 18013.529 | D72: =+A72+E72 -> 44622 | E72: 33 | F72: 0.39 | G72: BBVA RAMONA
A73: 44587 | B73: 144000 | C73: =B73+(B73*F73/365*E73)*1 -> 148615.89 | D73: =+A73+E73 -> 44617 | E73: 30 | F73: 0.39 | G73: BBVA
A74: 44589 | B74: 104000 | C74: =B74+(B74*F74/365*E74)*1 -> 107667.07 | D74: =+A74+E74 -> 44622 | E74: 33 | F74: 0.39 | G74: HSBC
A75: 44592 | B75: 165000 | C75: =B75+(B75*F75/365*E75)*1 -> 170289.04 | D75: =+A75+E75 -> 44622 | E75: 30 | F75: 0.39 | G75: BBVA RAMONA
... A77: 44589 | B77: 180000 | C77: =B77+(B77*F77/365*E77)*1 -> 186346.85 | D77: =+A77+E77 -> 44622 | E77: 33 | F77: 0.39 | G77: BBVA
A78: 44593 | B78: 15000 | C78: =B78+(B78*F78/365*E78)*1 -> 15496.849 | D78: =+A78+E78 -> 44624 | E78: 31 | F78: 0.39 | G78: CIUDAD | H78: =SUM(C78:C78) -> 15496.849
A79: 44594 | B79: 18700 | C79: =B79+(B79*F79/365*E79)*1 -> 19299.425 | D79: =+A79+E79 -> 44624 | E79: 30 | F79: 0.39 | G79: BBVA RAMONA | H79: =SUM(C79:C79) -> 19299.425
A80: 44594 | B80: 25000 | C80: =B80+(B80*F80/365*E80)*1 -> 25801.37 | D80: =+A80+E80 -> 44624 | E80: 30 | F80: 0.39 | G80: BBVA RAMONA
A81: 44592 | B81: 800000 | C81: =B81+(B81*F81/365*E81)*1 -> 825643.84 | D81: =+A81+E81 -> 44622 | E81: 30 | F81: 0.39 | G81: BBVA
A82: 44594 | B82: 30300 | C82: =B82+(B82*F82/365*E82)*1 -> 31271.26 | D82: =+A82+E82 -> 44624 | E82: 30 | F82: 0.39 | G82: CIUDAD
A83: 44594 | B83: 220000 | C83: =B83+(B83*F83/365*E83)*1 -> 227052.05 | D83: =+A83+E83 -> 44624 | E83: 30 | F83: 0.39 | G83: HSBC MARIA
A84: 44596 | B84: 22500 | C84: =B84+(B84*F84/365*E84)*1 -> 23245.274 | D84: =+A84+E84 -> 44627 | E84: 31 | F84: 0.39 | G84: CIUDAD
A85: 44601 | B85: 9500 | C85: =B85+(B85*F85/365*E85)*1 -> 9804.5205 | D85: =+A85+E85 -> 44631 | E85: 30 | F85: 0.39 | G85: CIUDAD
A86: 44594 | B86: 85000 | C86: =B86+(B86*F86/365*E86)*1 -> 87724.658 | D86: =+A86+E86 -> 44624 | E86: 30 | F86: 0.39 | G86: BBVA | H86: =SUM(C86:C86) -> 87724.658
A87: 44587 | B87: 192100 | C87: =B87+(B87*F87/365*E87)*1 -> 198257.73 | D87: =+A87+E87 -> 44617 | E87: 30 | F87: 0.39 | G87: BNA
A88: 44602 | B88: 18900 | C88: =B88+(B88*F88/365*E88)*1 -> 19546.225 | D88: =+A88+E88 -> 44634 | E88: 32 | F88: 0.39 | G88: BNA | H88: =SUM(C88:C88) -> 19546.225
A89: 44602 | B89: 100000 | C89: =B89+(B89*F89/365*E89)*1 -> 103419.18 | D89: =+A89+E89 -> 44634 | E89: 32 | F89: 0.39 | G89: BBVA
A90: 44603 | B90: 55000 | C90: =B90+(B90*F90/365*E90)*1 -> 56821.781 | D90: =+A90+E90 -> 44634 | E90: 31 | F90: 0.39 | G90: CIUDAD | H90: =SUM(C90:C90) -> 56821.781
A91: 44603 | B91: 20000 | C91: =B91+(B91*F91/365*E91)*1 -> 20662.466 | D91: =+A91+E91 -> 44634 | E91: 31 | F91: 0.39 | G91: HSBC
A92: 44608 | B92: 110000 | C92: =B92+(B92*F92/365*E92)*1 -> 113526.03 | D92: =+A92+E92 -> 44638 | E92: 30 | F92: 0.39 | G92: BBVA RAMONA
A93: 44608 | B93: 19800 | C93: =B93+(B93*F93/365*E93)*1 -> 20434.685 | D93: =+A93+E93 -> 44638 | E93: 30 | F93: 0.39 | G93: CIUDAD
A94: 44603 | B94: 140000 | C94: =B94+(B94*F94/365*E94)*1 -> 144637.26 | D94: =+A94+E94 -> 44634 | E94: 31 | F94: 0.39 | G94: BBVA
A95: 44602 | B95: 4000 | C95: =B95+(B95*F95/365*E95)*1 -> 4136.7671 | D95: =+A95+E95 -> 44634 | E95: 32 | F95: 0.39 | G95: BNA
A96: 44613 | B96: 55000 | C96: =B96+(B96*F96/365*E96)*1 -> 56876.027 | D96: =+A96+E96 -> 44643 | E96: 30 | F96: 0.415 | G96: HSBC MARIA
A97: 44613 | B97: 124000 | C97: =B97+(B97*F97/365*E97)*1 -> 128229.59 | D97: =+A97+E97 -> 44643 | E97: 30 | F97: 0.415 | G97: HSBC MARIA
A98: 44610 | B98: 82000 | C98: =B98+(B98*F98/365*E98)*1 -> 84890.219 | D98: =+A98+E98 -> 44641 | E98: 31 | F98: 0.415 | G98: BBVA
A99: 44615 | B99: 20600 | C99: =B99+(B99*F99/365*E99)*1 -> 21302.658 | D99: =+A99+E99 -> 44645 | E99: 30 | F99: 0.415 | G99: BBVA BARBARA
A100: 44615 | B100: 53400 | C100: =B100+(B100*F100/365*E100)*1 -> 55221.452 | D100: =+A100+E100 -> 44645 | E100: 30 | F100: 0.415 | G100: BBVA RAMONA
A101: 44610 | B101: 20000 | C101: =B101+(B101*F101/365*E101)*1 -> 20704.932 | D101: =+A101+E101 -> 44641 | E101: 31 | F101: 0.415 | G101: BNA
A102: 44615 | B102: 4190 | C102: =B102+(B102*F102/365*E102)*1 -> 4332.9192 | D102: =+A102+E102 -> 44645 | E102: 30 | F102: 0.415 | G102: CIUDAD
... A108: 44617 | B108: 73000 | C108: =B108+(B108*F108/365*E108)*1 -> 75573 | D108: =+A108+E108 -> 44648 | E108: 31 | F108: 0.415 | G108: HSBC MARIA
A109: 44617 | B109: 155000 | C109: =B109+(B109*F109/365*E109)*1 -> 160463.22 | D109: =+A109+E109 -> 44648 | E109: 31 | F109: 0.415 | G109: HSBC MARIA | H109: =SUM(C109:C109) -> 160463.22
A110: 44622 | B110: 36700 | C110: =B110+(B110*F110/365*E110)*1 -> 37951.822 | D110: =+A110+E110 -> 44652 | E110: 30 | F110: 0.415 | G110: BBVA BARBARA
A111: 44622 | B111: 124300 | C111: =B111+(B111*F111/365*E111)*1 -> 128539.82 | D111: =+A111+E111 -> 44652 | E111: 30 | F111: 0.415 | G111: BBVA RAMONA
A112: 44617 | B112: 148000 | C112: =B112+(B112*F112/365*E112)*1 -> 153216.49 | D112: =+A112+E112 -> 44648 | E112: 31 | F112: 0.415 | G112: BBVA
A113: 44622 | B113: 70000 | C113: =B113+(B113*F113/365*E113)*1 -> 72387.671 | D113: =+A113+E113 -> 44652 | E113: 30 | F113: 0.415 | G113: HSBC MARIA
A114: 44622 | B114: 60000 | C114: =B114+(B114*F114/365*E114)*1 -> 62046.575 | D114: =+A114+E114 -> 44652 | E114: 30 | F114: 0.415 | G114: HSBC
A115: 44617 | B115: 198300 | C115: =B115+(B115*F115/365*E115)*1 -> 205289.4 | D115: =+A115+E115 -> 44648 | E115: 31 | F115: 0.415 | G115: BNA
A116: 44624 | B116: 45000 | C116: =B116+(B116*F116/365*E116)*1 -> 46586.096 | D116: =+A116+E116 -> 44655 | E116: 31 | F116: 0.415 | G116: BBVA RAMONA
A117: 44622 | B117: 480000 | C117: =B117+(B117*F117/365*E117)*1 -> 496372.6 | D117: =+A117+E117 -> 44652 | E117: 30 | F117: 0.415 | G117: BBVA
A118: 44624 | B118: 46800 | C118: =B118+(B118*F118/365*E118)*1 -> 48449.54 | D118: =+A118+E118 -> 44655 | E118: 31 | F118: 0.415 | G118: CIUDAD
A119: 44624 | B119: 37000 | C119: =B119+(B119*F119/365*E119)*1 -> 38304.123 | D119: =+A119+E119 -> 44655 | E119: 31 | F119: 0.415 | G119: ITAU
A120: 44624 | B120: 115000 | C120: =B120+(B120*F120/365*E120)*1 -> 119053.36 | D120: =+A120+E120 -> 44655 | E120: 31 | F120: 0.415 | G120: HSBC MARIA
A121: 44622 | B121: 500000 | C121: =B121+(B121*F121/365*E121)*1 -> 590318.43 | D121: =+A121+E121 -> 44712 | E121: 90 | F121: 0.73258282 | G121: BBVA UVA | H121: =501232.88+89085.55 -> 590318.43
A122: 44631 | B122: 28800 | C122: =B122+(B122*F122/365*E122)*1 -> 29815.101 | D122: =+A122+E122 -> 44662 | E122: 31 | F122: 0.415 | G122: CIUDAD | H122: =SUM(C122:C122) -> 29815.101
A123: 44624 | B123: 85000 | C123: =B123+(B123*F123/365*E123)*1 -> 87995.959 | D123: =+A123+E123 -> 44655 | E123: 31 | F123: 0.415 | G123: BBVA
A124: 44634 | B124: 40000 | C124: =B124+(B124*F124/365*E124)*1 -> 41364.384 | D124: =+A124+E124 -> 44664 | E124: 30 | F124: 0.415 | G124: HSBC | H124: =SUM(C124:C124) -> 41364.384
A125: 44623 | B125: 19800 | C125: =B125+(B125*F125/365*E125)*1 -> 20520.395 | D125: =+A125+E125 -> 44655 | E125: 32 | F125: 0.415 | G125: BNA
A126: 44575 | B126: 43300 | C126: =B126+(B126*F126/365*E126)*1 -> 48949.96 | D126: =+A126+E126 -> 44669 | E126: 94 | F126: 0.50666685 | G126: ITAU UVA
A127: 44575 | B127: 115000 | C127: =B127+(B127*F127/365*E127)*1 -> 130006.36 | D127: =+A127+E127 -> 44669 | E127: 94 | F127: 0.50669023 | G127: BBVA UVA BARBARA
A128: 44627 | B128: 62000 | C128: =B128+(B128*F128/365*E128)*1 -> 64114.795 | D128: =+A128+E128 -> 44657 | E128: 30 | F128: 0.415 | G128: BBVA | H128: =SUM(C128:C128) -> 64114.795
A129: 44635 | B129: 23600 | C129: =B129+(B129*F129/365*E129)*1 -> 24512.318 | D129: =+A129+E129 -> 44669 | E129: 34 | F129: 0.415 | G129: BNA | H129: =SUM(C129:C129) -> 24512.318
A130: 44635 | B130: 25000 | C130: =B130+(B130*F130/365*E130)*1 -> 25966.438 | D130: =+A130+E130 -> 44669 | E130: 34 | F130: 0.415 | G130: BBVA BARBARA | H130: =115296.16+14710.2 -> 130006.36
A131: 44637 | B131: 17500 | C131: =B131+(B131*F131/365*E131)*1 -> 18136.712 | D131: =+A131+E131 -> 44669 | E131: 32 | F131: 0.415 | G131: BNA
A132: 44637 | B132: 31000 | C132: =B132+(B132*F132/365*E132)*1 -> 32127.89 | D132: =+A132+E132 -> 44669 | E132: 32 | F132: 0.415 | G132: BBVA RAMONA | H132: =SUM(C132:C132) -> 32127.89
A133: 44638 | B133: 47000 | C133: =B133+(B133*F133/365*E133)*1 -> 48656.589 | D133: =+A133+E133 -> 44669 | E133: 31 | F133: 0.415 | G133: BBVA RAMONA | H133: =SUM(C133:C133) -> 48656.589
A134: 44634 | B134: 140000 | C134: =B134+(B134*F134/365*E134)*1 -> 144775.34 | D134: =+A134+E134 -> 44664 | E134: 30 | F134: 0.415 | G134: BBVA | H134: =SUM(C134:C134) -> 144775.34
...

Sheet RES.ANT.
A1: descripcion | B1: importe | C1: mes
A2: AUSTRAL | B2: 800 | C2: 35004
A3: AUTO | B3: 250 | C3: 35004
A4: CATAMARCA | B4: 142 | C4: 35004
A5: IMPUESTOS | B5: =1500+1267+896+343 -> 4006 | C5: 35004
A6: NETO | B6: 16009 | C6: 35004
A7: AUTO | B7: =19800-7500-1000 -> 11300 | C7: 35034
A8: IMPUESTOS | B8: 398 | C8: 35034
A9: LAVALLE | B9: 53 | C9: 35034
A10: NETO | B10: =19346-6851 -> 12495 | C10: 35034 | D10: =SUBTOTAL(9,B6:B10) -> 40255
A11: PERSONALES | B11: =520+214 -> 734 | C11: 35034
A12: SAN JUAN | B12: =176+54.52 -> 230.52 | C12: 35034
A13: ALQUILER | B13: -380 | C13: 35065
A14: AUTO | B14: =100+220+46+315 -> 681 | C14: 35065
A15: IMPUESTOS | B15: =54.52+398 -> 452.52 | C15: 35065
A16: LAVALLE | B16: =70+60 -> 130 | C16: 35065
A17: NETO | B17: =18208.778337+555 -> 18763.778 | C17: 35065
A18: PERSONALES | B18: =100+60+150+10+130 -> 450 | C18: 35065
A19: SAN JUAN | B19: =34+40+29+180+24 -> 307 | C19: 35065
A20: ALQUILER | B20: -380 | C20: 35096
A21: AUTO | B21: =130+692 -> 822 | C21: 35096
A22: CATAMARCA | B22: 142 | C22: 35096
A23: IMPUESTOS | B23: =54.52+398 -> 452.52 | C23: 35096
A24: LANDIN | B24: 500 | C24: 35096
A25: LAVALLE | B25: 60 | C25: 35096
A26: NETO | B26: 17498 | C26: 35096
A27: PERSONALES | B27: =150+120+120 -> 390 | C27: 35096
A28: SAN JUAN | B28: =98+166+28 -> 292 | C28: 35096
A29: ALQUILER | B29: -280 | C29: 35125
A30: AUTO | B30: 119 | C30: 35125
A31: CATAMARCA | B31: 0 | C31: 35125
A32: IMPUESTOS | B32: 452.42 | C32: 35125
A33: LANDIN | B33: 0 | C33: 35125
A34: LAVALLE | B34: 120 | C34: 35125
A35: NETO | B35: 23068.549 | C35: 35125
A36: PERSONALES | B36: 555 | C36: 35125
A37: SAN JUAN | B37: 251 | C37: 35125
A38: ALQUILER | B38: -100 | C38: 35156
A39: AUTO | B39: 119 | C39: 35156
A40: CATAMARCA | B40: 142 | C40: 35156
... A117: CATAMARCA | B117: 142 | C117: 35400
A118: IMPUESTOS | B118: =1245+398 -> 1643 | C118: 35400
A119: JUNCAL | B119: =59.06+366.69+10.65+16.89 -> 453.29 | C119: 35400
A120: LANDIN | B120: 0 | C120: 35400
A121: LAVALLE | B121: 60 | C121: 35400
A122: NETO | B122: 27824 | C122: 35400 | D122: =SUBTOTAL(9,B17:B122) -> 312880.14
A123: PERSONALES | B123: =80+90+50+130+135+30+50+63+70+200+50 -> 948 | C123: 35400
A124: ALQUILER | B124: 0 | C124: 35431
A125: AUSTRAL | B125: 0 | C125: 35431
A126: AUTO | B126: =83+120+82 -> 285 | C126: 35431
A127: AVELLANEDA | B127: =500+22.81+4.72+74.34 -> 601.87 | C127: 35431
A128: CATAMARCA | B128: 0 | C128: 35431
A129: IMPUESTOS | B129: 838.83 | C129: 35431
A130: JUNCAL | B130: =31.87+7.89+118.16+61.25+390.77+37.81+23.4 -> 671.15 | C130: 35431
A131: LANDIN | B131: 0 | C131: 35431
A132: LAVALLE | B132: =12.95+60+6.42+51.45 -> 130.82 | C132: 35431
A133: NETO | B133: =-363+21986 -> 21623 | C133: 35431
A134: PERSONALES | B134: =50+50+30+30+150+60+30+35+100+80+50+20+60+150+30 -> 925 | C134: 35431
A135: AUSTRAL | B135: 0 | C135: 35462
A136: LAVALLE | B136: 0 | C136: 35462
A137: CATAMARCA | B137: 0 | C137: 35462
A138: ALQUILER | B138: -380 | C138: 35462
A139: IMPUESTOS | B139: 441.47 | C139: 35462
A140: AUTO | B140: 113.26 | C140: 35462
A141: LANDIN | B141: 400 | C141: 35462
A142: AVELLANEDA | B142: 440.93 | C142: 35462
A143: JUNCAL | B143: 495.87 | C143: 35462
A144: PERSONALES | B144: 1037 | C144: 35462
A145: NETO | B145: 74028.729 | C145: 35462
A146: AUSTRAL | B146: 614 | C146: 35490
... A160: ALQUILER | B160: 380 | C160: 35521
A161: IMPUESTOS | B161: =620.71+991.32+3.37+1003.78+197.79+200.47+12*173.27+12*170.96 -> 7148.2 | C161: 35521
A162: AUTO | B162: =120+120+120 -> 360 | C162: 35521
A163: LANDIN | B163: 0 | C163: 35521
A164: AVELLANEDA | B164: 0 | C164: 35521
A165: JUNCAL | B165: =305.75+57.19+16.89+44.35 -> 424.18 | C165: 35521
A166: PERSONALES | B166: =25+95+70+130+40+25+100+30 -> 515 | C166: 35521
A167: NETO | B167: 21605.586 | C167: 35521
A168: AUSTRAL | B168: 0 | C168: 35551
A169: LAVALLE | B169: =60+12.75+6.42+15.67+60 -> 154.84 | C169: 35551
A170: CATAMARCA | B170: 142 | C170: 35551
A171: ALQUILER | B171: 0 | C171: 35551
A172: IMPUESTOS | B172: 0 | C172: 35551
A173: AUTO | B173: 0 | C173: 35551
A174: LANDIN | B174: 0 | C174: 35551
A175: AVELLANEDA | B175: 0 | C175: 35551
A176: JUNCAL | B176: =317.98+53.71+118.16+57.5+1100 -> 1647.35 | C176: 35551
A177: PERSONALES | B177: =50+100+80 -> 230 | C177: 35551
A178: NETO | B178: 34427 | C178: 35551
A179: AUSTRAL | B179: 0 | C179: 35582
A180: LAVALLE | B180: 0 | C180: 35582
A181: CATAMARCA | B181: 0 | C181: 35582
A182: ALQUILER | B182: 0 | C182: 35582
A183: IMPUESTOS | B183: 1750.52 | C183: 35582
A184: AUTO | B184: 113.23 | C184: 35582
A185: LANDIN | B185: 0 | C185: 35582
A186: JUNCAL | B186: 3514.42 | C186: 35582
A187: PERSONALES | B187: 1660 | C187: 35582
A188: NETO | B188: =-600+30818.3157680639 -> 30218.316 | C188: 35582
A189: AUSTRAL | B189: 0 | C189: 35612
...
